[
    {
        "id": "p_35_2951",
        "question": "vị lãnh tụ kiệt xuất của nhân dân Ấn Độ là ai",
        "answer": "M. Ganđi",
        "context": "Ngày 30 - 1 1948, vị lãnh tụ kiệt xuất của nhân dân Ấn Độ là M. Ganđi bị bọn phản động ám sát, nhưng Đảng ' Quốc đại vẫn tiếp tục Iãnh đạo cuộc đấu tranh giành độc lập dân tộc."
    },
    {
        "id": "p_35_2952",
        "question": "lãnh tụ kiệt xuất của nhân dân Ấn Độ là ai",
        "answer": "M. Ganđi",
        "context": "Ngày 30 - 1 1948, vị lãnh tụ kiệt xuất của nhân dân Ấn Độ là M. Ganđi bị bọn phản động ám sát, nhưng Đảng ' Quốc đại vẫn tiếp tục Iãnh đạo cuộc đấu tranh giành độc lập dân tộc."
    },
    {
        "id": "p_35_2953",
        "question": "vị lãnh tụ kiệt xuất của Ấn Độ là ai",
        "answer": "M. Ganđi",
        "context": "Ngày 30 - 1 1948, vị lãnh tụ kiệt xuất của nhân dân Ấn Độ là M. Ganđi bị bọn phản động ám sát, nhưng Đảng ' Quốc đại vẫn tiếp tục Iãnh đạo cuộc đấu tranh giành độc lập dân tộc."
    },
    {
        "id": "p_35_2954",
        "question": "ai là vị lãnh tụ kiệt xuất của nhân dân Ấn Độ",
        "answer": "M. Ganđi",
        "context": "Ngày 30 - 1 1948, vị lãnh tụ kiệt xuất của nhân dân Ấn Độ là M. Ganđi bị bọn phản động ám sát, nhưng Đảng ' Quốc đại vẫn tiếp tục Iãnh đạo cuộc đấu tranh giành độc lập dân tộc."
    },
    {
        "id": "p_35_2955",
        "question": "vị lãnh tụ kiệt xuất của nhân dân Ấn Độ là ai?",
        "answer": "M. Ganđi",
        "context": "Ngày 30 - 1 1948, vị lãnh tụ kiệt xuất của nhân dân Ấn Độ là M. Ganđi bị bọn phản động ám sát, nhưng Đảng ' Quốc đại vẫn tiếp tục Iãnh đạo cuộc đấu tranh giành độc lập dân tộc."
    },
    {
        "id": "p_35_2956",
        "question": "ai là lãnh tụ kiệt xuất của nhân dân Ấn Độ",
        "answer": "M. Ganđi",
        "context": "Ngày 30 - 1 1948, vị lãnh tụ kiệt xuất của nhân dân Ấn Độ là M. Ganđi bị bọn phản động ám sát, nhưng Đảng ' Quốc đại vẫn tiếp tục Iãnh đạo cuộc đấu tranh giành độc lập dân tộc."
    },
    {
        "id": "p_35_2957",
        "question": "lãnh tụ kiệt xuất của Ấn Độ là ai",
        "answer": "M. Ganđi",
        "context": "Ngày 30 - 1 1948, vị lãnh tụ kiệt xuất của nhân dân Ấn Độ là M. Ganđi bị bọn phản động ám sát, nhưng Đảng ' Quốc đại vẫn tiếp tục Iãnh đạo cuộc đấu tranh giành độc lập dân tộc."
    },
    {
        "id": "p_35_2958",
        "question": "vị lãnh tụ kiệt xuất của nhân dân Ấn Độ là gì",
        "answer": "M. Ganđi",
        "context": "Ngày 30 - 1 1948, vị lãnh tụ kiệt xuất của nhân dân Ấn Độ là M. Ganđi bị bọn phản động ám sát, nhưng Đảng ' Quốc đại vẫn tiếp tục Iãnh đạo cuộc đấu tranh giành độc lập dân tộc."
    },
    {
        "id": "p_35_2959",
        "question": "vị lãnh tụ kiệt xuất của nhân dân Ấn Độ",
        "answer": "M. Ganđi",
        "context": "Ngày 30 - 1 1948, vị lãnh tụ kiệt xuất của nhân dân Ấn Độ là M. Ganđi bị bọn phản động ám sát, nhưng Đảng ' Quốc đại vẫn tiếp tục Iãnh đạo cuộc đấu tranh giành độc lập dân tộc."
    },
    {
        "id": "p_35_2960",
        "question": "ai là lãnh tụ kiệt xuất của Ấn Độ",
        "answer": "M. Ganđi",
        "context": "Ngày 30 - 1 1948, vị lãnh tụ kiệt xuất của nhân dân Ấn Độ là M. Ganđi bị bọn phản động ám sát, nhưng Đảng ' Quốc đại vẫn tiếp tục Iãnh đạo cuộc đấu tranh giành độc lập dân tộc."
    },
    {
        "id": "p_35_2961",
        "question": "đảng quốc đại nào đã lãnh đạo nhân dân tiếp tục cuộc đấu tranh giành độc lập",
        "answer": "Đảng Quốc đại do G. Nêru",
        "context": "Không thoả mãn với quy chế tự trị, Đảng Quốc đại do G. Nêru đứng đẩu đã lãnh đạo nhân dân tiếp tục cuộc đấu tranh giành độc lập trong những năm 1948 = 1950."
    },
    {
        "id": "p_35_2962",
        "question": "đảng nào đã lãnh đạo nhân dân tiếp tục cuộc đấu tranh giành độc lập",
        "answer": "Đảng Quốc đại",
        "context": "Không thoả mãn với quy chế tự trị, Đảng Quốc đại do G. Nêru đứng đẩu đã lãnh đạo nhân dân tiếp tục cuộc đấu tranh giành độc lập trong những năm 1948 = 1950."
    },
    {
        "id": "p_35_2963",
        "question": "đảng quốc đại nào đã lãnh đạo nhân dân tiếp tục cuộc đấu tranh giành độc lập?",
        "answer": "Đảng Quốc đại",
        "context": "Không thoả mãn với quy chế tự trị, Đảng Quốc đại do G. Nêru đứng đẩu đã lãnh đạo nhân dân tiếp tục cuộc đấu tranh giành độc lập trong những năm 1948 = 1950."
    },
    {
        "id": "p_35_2964",
        "question": "đảng nào đã lãnh đạo nhân dân tiếp tục cuộc đấu tranh giành độc lập?",
        "answer": "Đảng Quốc đại",
        "context": "Không thoả mãn với quy chế tự trị, Đảng Quốc đại do G. Nêru đứng đẩu đã lãnh đạo nhân dân tiếp tục cuộc đấu tranh giành độc lập trong những năm 1948 = 1950."
    },
    {
        "id": "p_35_2965",
        "question": "đảng quốc đại nào đã lãnh đạo nhân dân tiếp tục đấu tranh giành độc lập",
        "answer": "Đảng Quốc đại do G. Nêru",
        "context": "Không thoả mãn với quy chế tự trị, Đảng Quốc đại do G. Nêru đứng đẩu đã lãnh đạo nhân dân tiếp tục cuộc đấu tranh giành độc lập trong những năm 1948 = 1950."
    },
    {
        "id": "p_35_2966",
        "question": "đảng quốc đại nào đã lãnh đạo nhân dân tiếp tục cuộc đấu tranh giành độc lập vào năm 1948",
        "answer": "G. Nêru",
        "context": "Không thoả mãn với quy chế tự trị, Đảng Quốc đại do G. Nêru đứng đẩu đã lãnh đạo nhân dân tiếp tục cuộc đấu tranh giành độc lập trong những năm 1948 = 1950."
    },
    {
        "id": "p_35_2967",
        "question": "đảng quốc đại nào đã lãnh đạo nhân dân tiếp tục cuộc chiến giành độc lập",
        "answer": "Đảng Quốc đại do G. Nêru",
        "context": "Không thoả mãn với quy chế tự trị, Đảng Quốc đại do G. Nêru đứng đẩu đã lãnh đạo nhân dân tiếp tục cuộc đấu tranh giành độc lập trong những năm 1948 = 1950."
    },
    {
        "id": "p_35_2968",
        "question": "đảng quốc đại nào đã lãnh đạo nhân dân tiếp tục cuộc đấu tranh giành độc lập trong những năm 1948",
        "answer": "G. Nêru",
        "context": "Không thoả mãn với quy chế tự trị, Đảng Quốc đại do G. Nêru đứng đẩu đã lãnh đạo nhân dân tiếp tục cuộc đấu tranh giành độc lập trong những năm 1948 = 1950."
    },
    {
        "id": "p_35_2969",
        "question": "đảng quốc đại nào đã lãnh đạo nhân dân tiếp tục đấu tranh giành độc lập?",
        "answer": "Đảng Quốc đại",
        "context": "Không thoả mãn với quy chế tự trị, Đảng Quốc đại do G. Nêru đứng đẩu đã lãnh đạo nhân dân tiếp tục cuộc đấu tranh giành độc lập trong những năm 1948 = 1950."
    },
    {
        "id": "p_35_2970",
        "question": "đảng quốc đại nào đã lãnh đạo nhân dân tiếp tục cuộc đấu tranh giành độc lập vào năm 1948?",
        "answer": "Đảng Quốc đại do G. Nêru",
        "context": "Không thoả mãn với quy chế tự trị, Đảng Quốc đại do G. Nêru đứng đẩu đã lãnh đạo nhân dân tiếp tục cuộc đấu tranh giành độc lập trong những năm 1948 = 1950."
    },
    {
        "id": "p_35_2971",
        "question": "khi nào ẩn độ tuyên bố độc lập",
        "answer": "Ngày 26 = 1 - 1950,",
        "context": "Ngày 26 = 1 - 1950, Ẩn Độ tuyên bố độc lập và thành lập nước cộng hoà."
    },
    {
        "id": "p_35_2972",
        "question": "ẩn độ tuyên bố độc lập khi nào",
        "answer": "Ngày 26 = 1 - 1950,",
        "context": "Ngày 26 = 1 - 1950, Ẩn Độ tuyên bố độc lập và thành lập nước cộng hoà."
    },
    {
        "id": "p_35_2973",
        "question": "khi nào thì ẩn độ tuyên bố độc lập",
        "answer": "Ngày 26 = 1 - 1950,",
        "context": "Ngày 26 = 1 - 1950, Ẩn Độ tuyên bố độc lập và thành lập nước cộng hoà."
    },
    {
        "id": "p_35_2974",
        "question": "khi nào ẩn độ thành lập nước cộng hoà",
        "answer": "Ngày 26 = 1 - 1950,",
        "context": "Ngày 26 = 1 - 1950, Ẩn Độ tuyên bố độc lập và thành lập nước cộng hoà."
    },
    {
        "id": "p_35_2975",
        "question": "ẩn độ tuyên bố độc lập vào năm nào",
        "answer": "1950,",
        "context": "Ngày 26 = 1 - 1950, Ẩn Độ tuyên bố độc lập và thành lập nước cộng hoà."
    },
    {
        "id": "p_35_2976",
        "question": "khi nào nước cộng hoà được thành lập",
        "answer": "Ngày 26 = 1 - 1950,",
        "context": "Ngày 26 = 1 - 1950, Ẩn Độ tuyên bố độc lập và thành lập nước cộng hoà."
    },
    {
        "id": "p_35_2977",
        "question": "ẩn độ đã thành lập nước cộng hoà vào năm nào",
        "answer": "Ngày 26 = 1 - 1950,",
        "context": "Ngày 26 = 1 - 1950, Ẩn Độ tuyên bố độc lập và thành lập nước cộng hoà."
    },
    {
        "id": "p_35_2978",
        "question": "khi nào ẩn độ tuyên bố độc lập nước cộng hoà",
        "answer": "Ngày 26 = 1 - 1950,",
        "context": "Ngày 26 = 1 - 1950, Ẩn Độ tuyên bố độc lập và thành lập nước cộng hoà."
    },
    {
        "id": "p_35_2979",
        "question": "ẩn độ tuyên bố độc lập",
        "answer": "Ẩn Độ tuyên bố độc lập và thành lập nước cộng hoà.",
        "context": "Ngày 26 = 1 - 1950, Ẩn Độ tuyên bố độc lập và thành lập nước cộng hoà."
    },
    {
        "id": "p_35_2980",
        "question": "ẩn độ đã thành lập nước cộng hoà khi nào",
        "answer": "Ngày 26 = 1 - 1950,",
        "context": "Ngày 26 = 1 - 1950, Ẩn Độ tuyên bố độc lập và thành lập nước cộng hoà."
    },
    {
        "id": "p_35_2981",
        "question": "sư thành lập nước cộng hoà Ấn Độ có ảnh hưởng gì đến phong trào giải phóng dân tộc trên thế giới",
        "answer": "có ảnh hưởng quan trong đến phong trào giải phóng dân tộc trên thế giới.",
        "context": "Sư thành lập nước Cộng hoà Ấn Độ đánh dấu thắng lợi to lớn của nhân dân Ấn Độ, có ảnh hưởng quan trong đến phong trào giải phóng dân tộc trên thế giới. 2."
    },
    {
        "id": "p_35_2982",
        "question": "sư thành lập nước cộng hoà Ấn Độ ảnh hưởng như thế nào đến phong trào giải phóng dân tộc",
        "answer": "có ảnh hưởng quan trong đến phong trào giải phóng dân tộc trên thế giới.",
        "context": "Sư thành lập nước Cộng hoà Ấn Độ đánh dấu thắng lợi to lớn của nhân dân Ấn Độ, có ảnh hưởng quan trong đến phong trào giải phóng dân tộc trên thế giới. 2."
    },
    {
        "id": "p_35_2983",
        "question": "sư thành lập nước cộng hoà Ấn Độ có ảnh hưởng gì đến phong trào giải phóng dân tộc trên thế giới?",
        "answer": "có ảnh hưởng quan trong đến phong trào giải phóng dân tộc trên thế giới.",
        "context": "Sư thành lập nước Cộng hoà Ấn Độ đánh dấu thắng lợi to lớn của nhân dân Ấn Độ, có ảnh hưởng quan trong đến phong trào giải phóng dân tộc trên thế giới. 2."
    },
    {
        "id": "p_35_2984",
        "question": "sư thành lập nước cộng hoà Ấn Độ có ảnh hưởng gì đến phong trào giải phóng dân tộc",
        "answer": "có ảnh hưởng quan trong đến phong trào giải phóng dân tộc trên thế giới.",
        "context": "Sư thành lập nước Cộng hoà Ấn Độ đánh dấu thắng lợi to lớn của nhân dân Ấn Độ, có ảnh hưởng quan trong đến phong trào giải phóng dân tộc trên thế giới. 2."
    },
    {
        "id": "p_35_2985",
        "question": "tại sao sư thành lập nước cộng hoà Ấn Độ",
        "answer": "đánh dấu thắng lợi to lớn của nhân dân Ấn Độ,",
        "context": "Sư thành lập nước Cộng hoà Ấn Độ đánh dấu thắng lợi to lớn của nhân dân Ấn Độ, có ảnh hưởng quan trong đến phong trào giải phóng dân tộc trên thế giới. 2."
    },
    {
        "id": "p_35_2986",
        "question": "ý nghĩa của sư thành lập nước cộng hoà Ấn Độ",
        "answer": "đánh dấu thắng lợi to lớn của nhân dân Ấn Độ,",
        "context": "Sư thành lập nước Cộng hoà Ấn Độ đánh dấu thắng lợi to lớn của nhân dân Ấn Độ, có ảnh hưởng quan trong đến phong trào giải phóng dân tộc trên thế giới. 2."
    },
    {
        "id": "p_35_2987",
        "question": "sư thành lập nước cộng hoà Ấn Độ là gì",
        "answer": "đánh dấu thắng lợi to lớn của nhân dân Ấn Độ,",
        "context": "Sư thành lập nước Cộng hoà Ấn Độ đánh dấu thắng lợi to lớn của nhân dân Ấn Độ, có ảnh hưởng quan trong đến phong trào giải phóng dân tộc trên thế giới. 2."
    },
    {
        "id": "p_35_2988",
        "question": "sư thành lập nước cộng hoà Ấn Độ ảnh hưởng như thế nào đến phong trào giải phóng dân tộc?",
        "answer": "có ảnh hưởng quan trong đến phong trào giải phóng dân tộc trên thế giới.",
        "context": "Sư thành lập nước Cộng hoà Ấn Độ đánh dấu thắng lợi to lớn của nhân dân Ấn Độ, có ảnh hưởng quan trong đến phong trào giải phóng dân tộc trên thế giới. 2."
    },
    {
        "id": "p_35_2989",
        "question": "sư thành lập nước cộng hoà Ấn Độ ảnh hưởng gì đến phong trào giải phóng dân tộc trên thế giới",
        "answer": "đánh dấu thắng lợi to lớn của nhân dân Ấn Độ,",
        "context": "Sư thành lập nước Cộng hoà Ấn Độ đánh dấu thắng lợi to lớn của nhân dân Ấn Độ, có ảnh hưởng quan trong đến phong trào giải phóng dân tộc trên thế giới. 2."
    },
    {
        "id": "p_35_2990",
        "question": "ý nghĩa của sư thành lập nước cộng hoà Ấn Độ là gì",
        "answer": "đánh dấu thắng lợi to lớn của nhân dân Ấn Độ,",
        "context": "Sư thành lập nước Cộng hoà Ấn Độ đánh dấu thắng lợi to lớn của nhân dân Ấn Độ, có ảnh hưởng quan trong đến phong trào giải phóng dân tộc trên thế giới. 2."
    },
    {
        "id": "p_35_2991",
        "question": "công cuộc xây dựng đất nước là gì",
        "answer": "Ân Độ đạt được rinno.",
        "context": "Công cuộc xây dựng đất nước Trong thời kì xây dựng đất nước, Ân Độ đạt được rinno."
    },
    {
        "id": "p_35_2992",
        "question": "thời kỳ xây dựng đất nước là gì",
        "answer": "Ân Độ đạt được rinno.",
        "context": "Công cuộc xây dựng đất nước Trong thời kì xây dựng đất nước, Ân Độ đạt được rinno."
    },
    {
        "id": "p_35_2993",
        "question": "công cuộc xây dựng đất nước ở Ân Độ là gì",
        "answer": "đạt được rinno.",
        "context": "Công cuộc xây dựng đất nước Trong thời kì xây dựng đất nước, Ân Độ đạt được rinno."
    },
    {
        "id": "p_35_2994",
        "question": "công cuộc xây dựng đất nước của Ân Độ là gì",
        "answer": "đạt được rinno.",
        "context": "Công cuộc xây dựng đất nước Trong thời kì xây dựng đất nước, Ân Độ đạt được rinno."
    },
    {
        "id": "p_35_2995",
        "question": "thời kỳ xây dựng đất nước của Ân Độ là gì",
        "answer": "đạt được rinno.",
        "context": "Công cuộc xây dựng đất nước Trong thời kì xây dựng đất nước, Ân Độ đạt được rinno."
    },
    {
        "id": "p_35_2996",
        "question": "công cuộc xây dựng đất nước đã làm gì",
        "answer": "Ân Độ đạt được rinno.",
        "context": "Công cuộc xây dựng đất nước Trong thời kì xây dựng đất nước, Ân Độ đạt được rinno."
    },
    {
        "id": "p_35_2997",
        "question": "thời kỳ xây dựng đất nước ở Ân Độ là gì",
        "answer": "đạt được rinno.",
        "context": "Công cuộc xây dựng đất nước Trong thời kì xây dựng đất nước, Ân Độ đạt được rinno."
    },
    {
        "id": "p_35_2998",
        "question": "công cuộc xây dựng đất nước là gì?",
        "answer": "Ân Độ đạt được rinno.",
        "context": "Công cuộc xây dựng đất nước Trong thời kì xây dựng đất nước, Ân Độ đạt được rinno."
    },
    {
        "id": "p_35_2999",
        "question": "công cuộc xây dựng đất nước của Ân Độ là gì?",
        "answer": "đạt được rinno.",
        "context": "Công cuộc xây dựng đất nước Trong thời kì xây dựng đất nước, Ân Độ đạt được rinno."
    },
    {
        "id": "p_35_3000",
        "question": "thời kỳ xây dựng đất nước là gì?",
        "answer": "Ân Độ đạt được rinno.",
        "context": "Công cuộc xây dựng đất nước Trong thời kì xây dựng đất nước, Ân Độ đạt được rinno."
    },
    {
        "id": "p_35_3001",
        "question": "g,eru đã xây dựng cơ sở hạ tẩng hiện đại",
        "answer": "công nghiệp nặng, chế tạo máy;",
        "context": "G,eru (1889 1964) nhiêu thành tựu vê nông nghiệp và công nghiệp; đặc biệt là công nghiệp nặng, chế tạo máy; xây dựng cơ sở hạ tẩng hiện đại."
    },
    {
        "id": "p_35_3002",
        "question": "g,eru đã xây dựng những cơ sở hạ tẩng nào",
        "answer": "công nghiệp nặng, chế tạo máy;",
        "context": "G,eru (1889 1964) nhiêu thành tựu vê nông nghiệp và công nghiệp; đặc biệt là công nghiệp nặng, chế tạo máy; xây dựng cơ sở hạ tẩng hiện đại."
    },
    {
        "id": "p_35_3003",
        "question": "g,eru đã xây dựng cơ sở hạ tẩng như thế nào",
        "answer": "hiện đại.",
        "context": "G,eru (1889 1964) nhiêu thành tựu vê nông nghiệp và công nghiệp; đặc biệt là công nghiệp nặng, chế tạo máy; xây dựng cơ sở hạ tẩng hiện đại."
    },
    {
        "id": "p_35_3004",
        "question": "g,eru đã xây dựng cơ sở hạ tẩng",
        "answer": "nhiêu thành tựu vê nông nghiệp và công nghiệp;",
        "context": "G,eru (1889 1964) nhiêu thành tựu vê nông nghiệp và công nghiệp; đặc biệt là công nghiệp nặng, chế tạo máy; xây dựng cơ sở hạ tẩng hiện đại."
    },
    {
        "id": "p_35_3005",
        "question": "g,eru đã xây dựng cơ sở hạ tẩng nào",
        "answer": "cơ sở hạ tẩng hiện đại.",
        "context": "G,eru (1889 1964) nhiêu thành tựu vê nông nghiệp và công nghiệp; đặc biệt là công nghiệp nặng, chế tạo máy; xây dựng cơ sở hạ tẩng hiện đại."
    },
    {
        "id": "p_35_3006",
        "question": "g,eru đã xây dựng cơ sở hạ tẩng hiện đại như thế nào",
        "answer": "công nghiệp nặng, chế tạo máy;",
        "context": "G,eru (1889 1964) nhiêu thành tựu vê nông nghiệp và công nghiệp; đặc biệt là công nghiệp nặng, chế tạo máy; xây dựng cơ sở hạ tẩng hiện đại."
    },
    {
        "id": "p_35_3007",
        "question": "g,eru đã xây dựng cơ sở hạ tẩng hiện đại vào năm nào",
        "answer": "(1889 1964)",
        "context": "G,eru (1889 1964) nhiêu thành tựu vê nông nghiệp và công nghiệp; đặc biệt là công nghiệp nặng, chế tạo máy; xây dựng cơ sở hạ tẩng hiện đại."
    },
    {
        "id": "p_35_3008",
        "question": "g,eru đã xây dựng những công ty nào",
        "answer": "công nghiệp nặng, chế tạo máy;",
        "context": "G,eru (1889 1964) nhiêu thành tựu vê nông nghiệp và công nghiệp; đặc biệt là công nghiệp nặng, chế tạo máy; xây dựng cơ sở hạ tẩng hiện đại."
    },
    {
        "id": "p_35_3009",
        "question": "g,eru đã xây dựng cơ sở hạ tẩng hiện đại như thế nào?",
        "answer": "công nghiệp nặng, chế tạo máy;",
        "context": "G,eru (1889 1964) nhiêu thành tựu vê nông nghiệp và công nghiệp; đặc biệt là công nghiệp nặng, chế tạo máy; xây dựng cơ sở hạ tẩng hiện đại."
    },
    {
        "id": "p_35_3010",
        "question": "g,eru đã xây dựng cơ sở hạ tẩng như thế nào?",
        "answer": "hiện đại.",
        "context": "G,eru (1889 1964) nhiêu thành tựu vê nông nghiệp và công nghiệp; đặc biệt là công nghiệp nặng, chế tạo máy; xây dựng cơ sở hạ tẩng hiện đại."
    },
    {
        "id": "p_35_3011",
        "question": "nước xuất khẩu gạo đứng hàng thứ ba trên thế giới",
        "answer": "Ấn Độ đã tự túc được lương thực,",
        "context": "Nhờ tiến hành cuộc \"cách mang xanh trong nông nghiệp; từ giữa những năm 70 của thế kỉ XX, Ấn Độ đã tự túc được lương thực, và từ năm 1995, là nước xuất khẩu gạo đứng hàng thứ ba trên thế giới."
    },
    {
        "id": "p_35_3012",
        "question": "Ấn Độ đã tự túc được lương thực vào năm nào",
        "answer": "giữa những năm 70 của thế kỉ XX,",
        "context": "Nhờ tiến hành cuộc \"cách mang xanh trong nông nghiệp; từ giữa những năm 70 của thế kỉ XX, Ấn Độ đã tự túc được lương thực, và từ năm 1995, là nước xuất khẩu gạo đứng hàng thứ ba trên thế giới."
    },
    {
        "id": "p_35_3013",
        "question": "Ấn Độ có phải là nước xuất khẩu gạo đứng hàng thứ ba trên thế giới không",
        "answer": "Ấn Độ đã tự túc được lương thực, và từ năm 1995,",
        "context": "Nhờ tiến hành cuộc \"cách mang xanh trong nông nghiệp; từ giữa những năm 70 của thế kỉ XX, Ấn Độ đã tự túc được lương thực, và từ năm 1995, là nước xuất khẩu gạo đứng hàng thứ ba trên thế giới."
    },
    {
        "id": "p_35_3014",
        "question": "Ấn Độ đã tự túc được lương thực như thế nào",
        "answer": "từ giữa những năm 70 của thế kỉ XX,",
        "context": "Nhờ tiến hành cuộc \"cách mang xanh trong nông nghiệp; từ giữa những năm 70 của thế kỉ XX, Ấn Độ đã tự túc được lương thực, và từ năm 1995, là nước xuất khẩu gạo đứng hàng thứ ba trên thế giới."
    },
    {
        "id": "p_35_3015",
        "question": "Ấn Độ đã tự túc được lương thực khi nào",
        "answer": "giữa những năm 70 của thế kỉ XX,",
        "context": "Nhờ tiến hành cuộc \"cách mang xanh trong nông nghiệp; từ giữa những năm 70 của thế kỉ XX, Ấn Độ đã tự túc được lương thực, và từ năm 1995, là nước xuất khẩu gạo đứng hàng thứ ba trên thế giới."
    },
    {
        "id": "p_35_3016",
        "question": "Ấn Độ được biết đến với cái gì",
        "answer": "nước xuất khẩu gạo đứng hàng thứ ba trên thế giới.",
        "context": "Nhờ tiến hành cuộc \"cách mang xanh trong nông nghiệp; từ giữa những năm 70 của thế kỉ XX, Ấn Độ đã tự túc được lương thực, và từ năm 1995, là nước xuất khẩu gạo đứng hàng thứ ba trên thế giới."
    },
    {
        "id": "p_35_3017",
        "question": "nước xuất khẩu gạo đứng hàng thứ ba trên thế giới là khi nào",
        "answer": "năm 1995,",
        "context": "Nhờ tiến hành cuộc \"cách mang xanh trong nông nghiệp; từ giữa những năm 70 của thế kỉ XX, Ấn Độ đã tự túc được lương thực, và từ năm 1995, là nước xuất khẩu gạo đứng hàng thứ ba trên thế giới."
    },
    {
        "id": "p_35_3018",
        "question": "nước xuất khẩu gạo đứng hàng thứ ba trên thế giới vào năm nào",
        "answer": "năm 1995,",
        "context": "Nhờ tiến hành cuộc \"cách mang xanh trong nông nghiệp; từ giữa những năm 70 của thế kỉ XX, Ấn Độ đã tự túc được lương thực, và từ năm 1995, là nước xuất khẩu gạo đứng hàng thứ ba trên thế giới."
    },
    {
        "id": "p_35_3019",
        "question": "Ấn Độ có phải là nước xuất khẩu gạo đứng hàng thứ ba trên thế giới không?",
        "answer": "Ấn Độ đã tự túc được lương thực,",
        "context": "Nhờ tiến hành cuộc \"cách mang xanh trong nông nghiệp; từ giữa những năm 70 của thế kỉ XX, Ấn Độ đã tự túc được lương thực, và từ năm 1995, là nước xuất khẩu gạo đứng hàng thứ ba trên thế giới."
    },
    {
        "id": "p_35_3020",
        "question": "Ấn Độ tự túc được lương thực khi nào",
        "answer": "giữa những năm 70 của thế kỉ XX,",
        "context": "Nhờ tiến hành cuộc \"cách mang xanh trong nông nghiệp; từ giữa những năm 70 của thế kỉ XX, Ấn Độ đã tự túc được lương thực, và từ năm 1995, là nước xuất khẩu gạo đứng hàng thứ ba trên thế giới."
    },
    {
        "id": "p_35_3021",
        "question": "năng lượng hạt nhân được sử dụng để làm gì",
        "answer": "sản xuất điện.",
        "context": "Cũng trong những năm 70, Ấn Độ đã sử dụng năng lượng hạt nhân vào sản xuất điện. Trong những năm 80, Ấn Độ đứng hàng thứ mười trong những nước sản xuất công nghiệp lớn nhất thế giới."
    },
    {
        "id": "p_35_3022",
        "question": "Ấn Độ sử dụng năng lượng hạt nhân như thế nào",
        "answer": "sản xuất điện.",
        "context": "Cũng trong những năm 70, Ấn Độ đã sử dụng năng lượng hạt nhân vào sản xuất điện. Trong những năm 80, Ấn Độ đứng hàng thứ mười trong những nước sản xuất công nghiệp lớn nhất thế giới."
    },
    {
        "id": "p_35_3023",
        "question": "Ấn Độ đã sử dụng năng lượng hạt nhân như thế nào",
        "answer": "sản xuất điện.",
        "context": "Cũng trong những năm 70, Ấn Độ đã sử dụng năng lượng hạt nhân vào sản xuất điện. Trong những năm 80, Ấn Độ đứng hàng thứ mười trong những nước sản xuất công nghiệp lớn nhất thế giới."
    },
    {
        "id": "p_35_3024",
        "question": "năng lượng hạt nhân được sử dụng để làm gì ở Ấn Độ",
        "answer": "sản xuất điện.",
        "context": "Cũng trong những năm 70, Ấn Độ đã sử dụng năng lượng hạt nhân vào sản xuất điện. Trong những năm 80, Ấn Độ đứng hàng thứ mười trong những nước sản xuất công nghiệp lớn nhất thế giới."
    },
    {
        "id": "p_35_3025",
        "question": "Ấn Độ sử dụng năng lượng gì",
        "answer": "năng lượng hạt nhân",
        "context": "Cũng trong những năm 70, Ấn Độ đã sử dụng năng lượng hạt nhân vào sản xuất điện. Trong những năm 80, Ấn Độ đứng hàng thứ mười trong những nước sản xuất công nghiệp lớn nhất thế giới."
    },
    {
        "id": "p_35_3026",
        "question": "Ấn Độ sử dụng loại năng lượng nào",
        "answer": "năng lượng hạt nhân",
        "context": "Cũng trong những năm 70, Ấn Độ đã sử dụng năng lượng hạt nhân vào sản xuất điện. Trong những năm 80, Ấn Độ đứng hàng thứ mười trong những nước sản xuất công nghiệp lớn nhất thế giới."
    },
    {
        "id": "p_35_3027",
        "question": "Ấn Độ đã sử dụng năng lượng gì",
        "answer": "năng lượng hạt nhân",
        "context": "Cũng trong những năm 70, Ấn Độ đã sử dụng năng lượng hạt nhân vào sản xuất điện. Trong những năm 80, Ấn Độ đứng hàng thứ mười trong những nước sản xuất công nghiệp lớn nhất thế giới."
    },
    {
        "id": "p_35_3028",
        "question": "năng lượng hạt nhân được sử dụng ở Ấn Độ như thế nào",
        "answer": "sản xuất điện.",
        "context": "Cũng trong những năm 70, Ấn Độ đã sử dụng năng lượng hạt nhân vào sản xuất điện. Trong những năm 80, Ấn Độ đứng hàng thứ mười trong những nước sản xuất công nghiệp lớn nhất thế giới."
    },
    {
        "id": "p_35_3029",
        "question": "năng lượng hạt nhân được sử dụng để làm gì?",
        "answer": "sản xuất điện.",
        "context": "Cũng trong những năm 70, Ấn Độ đã sử dụng năng lượng hạt nhân vào sản xuất điện. Trong những năm 80, Ấn Độ đứng hàng thứ mười trong những nước sản xuất công nghiệp lớn nhất thế giới."
    },
    {
        "id": "p_35_3030",
        "question": "Ấn Độ đã sử dụng năng lượng hạt nhân để làm gì",
        "answer": "sản xuất điện.",
        "context": "Cũng trong những năm 70, Ấn Độ đã sử dụng năng lượng hạt nhân vào sản xuất điện. Trong những năm 80, Ấn Độ đứng hàng thứ mười trong những nước sản xuất công nghiệp lớn nhất thế giới."
    },
    {
        "id": "p_35_3031",
        "question": "Ấn Độ đã chế tạo được những loại thiết bị nào",
        "answer": "máy móc,",
        "context": "Ấn Độ đã chế tạo được máy móc, thiết bị ngành dệt, hoá chất, máy bay; tàu thuỷ, đẩu máy xe lửa, ti vi màu v. v. tốc độ tăng trưởng GDP năm 1995 là 7,4%, năm 2000 là 3,9%."
    },
    {
        "id": "p_35_3032",
        "question": "Ấn Độ đã chế tạo được những gì",
        "answer": "máy móc,",
        "context": "Ấn Độ đã chế tạo được máy móc, thiết bị ngành dệt, hoá chất, máy bay; tàu thuỷ, đẩu máy xe lửa, ti vi màu v. v. tốc độ tăng trưởng GDP năm 1995 là 7,4%, năm 2000 là 3,9%."
    },
    {
        "id": "p_35_3033",
        "question": "Ấn Độ chế tạo được những loại thiết bị nào",
        "answer": "máy móc,",
        "context": "Ấn Độ đã chế tạo được máy móc, thiết bị ngành dệt, hoá chất, máy bay; tàu thuỷ, đẩu máy xe lửa, ti vi màu v. v. tốc độ tăng trưởng GDP năm 1995 là 7,4%, năm 2000 là 3,9%."
    },
    {
        "id": "p_35_3034",
        "question": "Ấn Độ chế tạo được những gì",
        "answer": "máy móc, thiết bị",
        "context": "Ấn Độ đã chế tạo được máy móc, thiết bị ngành dệt, hoá chất, máy bay; tàu thuỷ, đẩu máy xe lửa, ti vi màu v. v. tốc độ tăng trưởng GDP năm 1995 là 7,4%, năm 2000 là 3,9%."
    },
    {
        "id": "p_35_3035",
        "question": "Ấn Độ đã chế tạo được những loại máy móc nào",
        "answer": "máy móc, thiết bị ngành dệt, hoá chất, máy bay;",
        "context": "Ấn Độ đã chế tạo được máy móc, thiết bị ngành dệt, hoá chất, máy bay; tàu thuỷ, đẩu máy xe lửa, ti vi màu v. v. tốc độ tăng trưởng GDP năm 1995 là 7,4%, năm 2000 là 3,9%."
    },
    {
        "id": "p_35_3036",
        "question": "Ấn Độ đã chế tạo được những thiết bị gì",
        "answer": "máy móc,",
        "context": "Ấn Độ đã chế tạo được máy móc, thiết bị ngành dệt, hoá chất, máy bay; tàu thuỷ, đẩu máy xe lửa, ti vi màu v. v. tốc độ tăng trưởng GDP năm 1995 là 7,4%, năm 2000 là 3,9%."
    },
    {
        "id": "p_35_3037",
        "question": "Ấn Độ đã chế tạo được gì",
        "answer": "máy móc, thiết bị",
        "context": "Ấn Độ đã chế tạo được máy móc, thiết bị ngành dệt, hoá chất, máy bay; tàu thuỷ, đẩu máy xe lửa, ti vi màu v. v. tốc độ tăng trưởng GDP năm 1995 là 7,4%, năm 2000 là 3,9%."
    },
    {
        "id": "p_35_3038",
        "question": "Ấn Độ đã chế tạo được những ngành gì",
        "answer": "máy móc, thiết bị",
        "context": "Ấn Độ đã chế tạo được máy móc, thiết bị ngành dệt, hoá chất, máy bay; tàu thuỷ, đẩu máy xe lửa, ti vi màu v. v. tốc độ tăng trưởng GDP năm 1995 là 7,4%, năm 2000 là 3,9%."
    },
    {
        "id": "p_35_3039",
        "question": "Ấn Độ đã chế tạo được bao nhiêu thiết bị",
        "answer": "máy móc, thiết bị",
        "context": "Ấn Độ đã chế tạo được máy móc, thiết bị ngành dệt, hoá chất, máy bay; tàu thuỷ, đẩu máy xe lửa, ti vi màu v. v. tốc độ tăng trưởng GDP năm 1995 là 7,4%, năm 2000 là 3,9%."
    },
    {
        "id": "p_35_3040",
        "question": "Ấn Độ đã chế tạo được những loại thiết bị nào?",
        "answer": "máy móc,",
        "context": "Ấn Độ đã chế tạo được máy móc, thiết bị ngành dệt, hoá chất, máy bay; tàu thuỷ, đẩu máy xe lửa, ti vi màu v. v. tốc độ tăng trưởng GDP năm 1995 là 7,4%, năm 2000 là 3,9%."
    },
    {
        "id": "p_35_3041",
        "question": "Ấn Độ có phải là một cường quốc sản xuất phẩn mêm không",
        "answer": "lớn nhất thế giới.",
        "context": "Trong các lĩnh vực khoa học kĩ thuật; văn hoá, giáo dục , Ấn Độ có những bước tiến nhanh chóng và hiện nay dang cố gắng vươn lên hàng các cường quốc về công nohê nhẩn mêm côno nohê hat nhân côno nohê Cuôc ach mauno châ Xám đã đưa Ấn Độ trở thành một trong những cường quốc sản xuất phẩn mêm lớn nhất thế giới."
    },
    {
        "id": "p_35_3042",
        "question": "Ấn Độ có phải là một cường quốc sản xuất phẩn mêm lớn nhất không",
        "answer": "thế giới.",
        "context": "Trong các lĩnh vực khoa học kĩ thuật; văn hoá, giáo dục , Ấn Độ có những bước tiến nhanh chóng và hiện nay dang cố gắng vươn lên hàng các cường quốc về công nohê nhẩn mêm côno nohê hat nhân côno nohê Cuôc ach mauno châ Xám đã đưa Ấn Độ trở thành một trong những cường quốc sản xuất phẩn mêm lớn nhất thế giới."
    },
    {
        "id": "p_35_3044",
        "question": "Ấn Độ có phải là một cường quốc sản xuất phẩn mêm lớn nhất thế giới không",
        "answer": "Cuôc ach mauno châ Xám",
        "context": "Trong các lĩnh vực khoa học kĩ thuật; văn hoá, giáo dục , Ấn Độ có những bước tiến nhanh chóng và hiện nay dang cố gắng vươn lên hàng các cường quốc về công nohê nhẩn mêm côno nohê hat nhân côno nohê Cuôc ach mauno châ Xám đã đưa Ấn Độ trở thành một trong những cường quốc sản xuất phẩn mêm lớn nhất thế giới."
    },
    {
        "id": "p_35_3045",
        "question": "Ấn Độ có phải là cường quốc sản xuất phẩn mêm không",
        "answer": "lớn nhất thế giới.",
        "context": "Trong các lĩnh vực khoa học kĩ thuật; văn hoá, giáo dục , Ấn Độ có những bước tiến nhanh chóng và hiện nay dang cố gắng vươn lên hàng các cường quốc về công nohê nhẩn mêm côno nohê hat nhân côno nohê Cuôc ach mauno châ Xám đã đưa Ấn Độ trở thành một trong những cường quốc sản xuất phẩn mêm lớn nhất thế giới."
    },
    {
        "id": "p_35_3046",
        "question": "Ấn Độ có phải là một cường quốc sản xuất phẩn mêm lớn nhất",
        "answer": "Cuôc ach mauno châ Xám",
        "context": "Trong các lĩnh vực khoa học kĩ thuật; văn hoá, giáo dục , Ấn Độ có những bước tiến nhanh chóng và hiện nay dang cố gắng vươn lên hàng các cường quốc về công nohê nhẩn mêm côno nohê hat nhân côno nohê Cuôc ach mauno châ Xám đã đưa Ấn Độ trở thành một trong những cường quốc sản xuất phẩn mêm lớn nhất thế giới."
    },
    {
        "id": "p_35_3047",
        "question": "Ấn Độ có phải là cường quốc sản xuất phẩn mêm lớn nhất thế giới không",
        "answer": "Cuôc ach mauno châ Xám",
        "context": "Trong các lĩnh vực khoa học kĩ thuật; văn hoá, giáo dục , Ấn Độ có những bước tiến nhanh chóng và hiện nay dang cố gắng vươn lên hàng các cường quốc về công nohê nhẩn mêm côno nohê hat nhân côno nohê Cuôc ach mauno châ Xám đã đưa Ấn Độ trở thành một trong những cường quốc sản xuất phẩn mêm lớn nhất thế giới."
    },
    {
        "id": "p_35_3048",
        "question": "Ấn Độ có phải là một cường quốc sản xuất phẩn mêm không?",
        "answer": "lớn nhất thế giới.",
        "context": "Trong các lĩnh vực khoa học kĩ thuật; văn hoá, giáo dục , Ấn Độ có những bước tiến nhanh chóng và hiện nay dang cố gắng vươn lên hàng các cường quốc về công nohê nhẩn mêm côno nohê hat nhân côno nohê Cuôc ach mauno châ Xám đã đưa Ấn Độ trở thành một trong những cường quốc sản xuất phẩn mêm lớn nhất thế giới."
    },
    {
        "id": "p_35_3049",
        "question": "Ấn Độ có phải là cường quốc sản xuất phẩn mêm lớn nhất không",
        "answer": "thế giới.",
        "context": "Trong các lĩnh vực khoa học kĩ thuật; văn hoá, giáo dục , Ấn Độ có những bước tiến nhanh chóng và hiện nay dang cố gắng vươn lên hàng các cường quốc về công nohê nhẩn mêm côno nohê hat nhân côno nohê Cuôc ach mauno châ Xám đã đưa Ấn Độ trở thành một trong những cường quốc sản xuất phẩn mêm lớn nhất thế giới."
    },
    {
        "id": "p_35_3050",
        "question": "Ấn Độ sản xuất phẩn mêm gì",
        "answer": "phẩn mêm lớn nhất thế giới.",
        "context": "Trong các lĩnh vực khoa học kĩ thuật; văn hoá, giáo dục , Ấn Độ có những bước tiến nhanh chóng và hiện nay dang cố gắng vươn lên hàng các cường quốc về công nohê nhẩn mêm côno nohê hat nhân côno nohê Cuôc ach mauno châ Xám đã đưa Ấn Độ trở thành một trong những cường quốc sản xuất phẩn mêm lớn nhất thế giới."
    },
    {
        "id": "p_35_3051",
        "question": "vệ tinh nhân tạo hoạt động như thế nào ở Ấn Độ",
        "answer": "7 vệ tinh nhân tạo hoạt động trong vũ trụ.",
        "context": "Năm 1974, Ấn Độ thử thành công bom nguyên tử năm 1975, phóng vệ tinh nhân tạo lên quỹ đao Trái Đất bằng tên lửa của mình. Đến năm 2002, Ấn Độ đã có 7 vệ tinh nhân tạo hoạt động trong vũ trụ."
    },
    {
        "id": "p_35_3052",
        "question": "Ấn Độ có bao nhiêu vệ tinh nhân tạo",
        "answer": "7 vệ tinh nhân tạo",
        "context": "Năm 1974, Ấn Độ thử thành công bom nguyên tử năm 1975, phóng vệ tinh nhân tạo lên quỹ đao Trái Đất bằng tên lửa của mình. Đến năm 2002, Ấn Độ đã có 7 vệ tinh nhân tạo hoạt động trong vũ trụ."
    },
    {
        "id": "p_35_3053",
        "question": "Ấn Độ đã thử bom nguyên tử vào năm nào",
        "answer": "Năm 1974,",
        "context": "Năm 1974, Ấn Độ thử thành công bom nguyên tử năm 1975, phóng vệ tinh nhân tạo lên quỹ đao Trái Đất bằng tên lửa của mình. Đến năm 2002, Ấn Độ đã có 7 vệ tinh nhân tạo hoạt động trong vũ trụ."
    },
    {
        "id": "p_35_3054",
        "question": "Ấn Độ thử bom nguyên tử vào năm nào",
        "answer": "Năm 1974,",
        "context": "Năm 1974, Ấn Độ thử thành công bom nguyên tử năm 1975, phóng vệ tinh nhân tạo lên quỹ đao Trái Đất bằng tên lửa của mình. Đến năm 2002, Ấn Độ đã có 7 vệ tinh nhân tạo hoạt động trong vũ trụ."
    },
    {
        "id": "p_35_3055",
        "question": "Ấn Độ đã thử bom nguyên tử khi nào",
        "answer": "năm 1975,",
        "context": "Năm 1974, Ấn Độ thử thành công bom nguyên tử năm 1975, phóng vệ tinh nhân tạo lên quỹ đao Trái Đất bằng tên lửa của mình. Đến năm 2002, Ấn Độ đã có 7 vệ tinh nhân tạo hoạt động trong vũ trụ."
    },
    {
        "id": "p_35_3056",
        "question": "bom nguyên tử được phát minh khi nào",
        "answer": "năm 1975,",
        "context": "Năm 1974, Ấn Độ thử thành công bom nguyên tử năm 1975, phóng vệ tinh nhân tạo lên quỹ đao Trái Đất bằng tên lửa của mình. Đến năm 2002, Ấn Độ đã có 7 vệ tinh nhân tạo hoạt động trong vũ trụ."
    },
    {
        "id": "p_35_3057",
        "question": "vệ tinh nhân tạo hoạt động như thế nào",
        "answer": "Ấn Độ đã có 7 vệ tinh nhân tạo hoạt động trong vũ trụ.",
        "context": "Năm 1974, Ấn Độ thử thành công bom nguyên tử năm 1975, phóng vệ tinh nhân tạo lên quỹ đao Trái Đất bằng tên lửa của mình. Đến năm 2002, Ấn Độ đã có 7 vệ tinh nhân tạo hoạt động trong vũ trụ."
    },
    {
        "id": "p_35_3058",
        "question": "Ấn Độ thử bom nguyên tử khi nào",
        "answer": "năm 1975,",
        "context": "Năm 1974, Ấn Độ thử thành công bom nguyên tử năm 1975, phóng vệ tinh nhân tạo lên quỹ đao Trái Đất bằng tên lửa của mình. Đến năm 2002, Ấn Độ đã có 7 vệ tinh nhân tạo hoạt động trong vũ trụ."
    },
    {
        "id": "p_35_3059",
        "question": "Ấn Độ có bao nhiêu bom nguyên tử",
        "answer": "7",
        "context": "Năm 1974, Ấn Độ thử thành công bom nguyên tử năm 1975, phóng vệ tinh nhân tạo lên quỹ đao Trái Đất bằng tên lửa của mình. Đến năm 2002, Ấn Độ đã có 7 vệ tinh nhân tạo hoạt động trong vũ trụ."
    },
    {
        "id": "p_35_3060",
        "question": "vệ tinh nhân tạo được phát minh khi nào",
        "answer": "năm 2002,",
        "context": "Năm 1974, Ấn Độ thử thành công bom nguyên tử năm 1975, phóng vệ tinh nhân tạo lên quỹ đao Trái Đất bằng tên lửa của mình. Đến năm 2002, Ấn Độ đã có 7 vệ tinh nhân tạo hoạt động trong vũ trụ."
    },
    {
        "id": "p_35_3061",
        "question": "Ấn Độ theo đuổi chính sách hoà bình nào",
        "answer": "trung lập tích cực,",
        "context": "Về đối ngoại, Ấn Độ theo đuổi chính sách hoà bình, trung lập tích cực, luôn luôn ủng hộ cuộc đấu tranh giành độc lập của các dân tộc."
    },
    {
        "id": "p_35_3062",
        "question": "Ấn Độ theo đuổi chính sách gì",
        "answer": "hoà bình, trung lập tích cực,",
        "context": "Về đối ngoại, Ấn Độ theo đuổi chính sách hoà bình, trung lập tích cực, luôn luôn ủng hộ cuộc đấu tranh giành độc lập của các dân tộc."
    },
    {
        "id": "p_35_3063",
        "question": "Ấn Độ theo đuổi chính sách hoà bình như thế nào",
        "answer": "trung lập tích cực,",
        "context": "Về đối ngoại, Ấn Độ theo đuổi chính sách hoà bình, trung lập tích cực, luôn luôn ủng hộ cuộc đấu tranh giành độc lập của các dân tộc."
    },
    {
        "id": "p_35_3064",
        "question": "Ấn Độ theo đuổi chính sách nào",
        "answer": "hoà bình, trung lập tích cực,",
        "context": "Về đối ngoại, Ấn Độ theo đuổi chính sách hoà bình, trung lập tích cực, luôn luôn ủng hộ cuộc đấu tranh giành độc lập của các dân tộc."
    },
    {
        "id": "p_35_3065",
        "question": "chính sách hoà bình của Ấn Độ là gì",
        "answer": "trung lập tích cực,",
        "context": "Về đối ngoại, Ấn Độ theo đuổi chính sách hoà bình, trung lập tích cực, luôn luôn ủng hộ cuộc đấu tranh giành độc lập của các dân tộc."
    },
    {
        "id": "p_35_3066",
        "question": "Ấn Độ theo đuổi chính sách hoà bình nào?",
        "answer": "hoà bình,",
        "context": "Về đối ngoại, Ấn Độ theo đuổi chính sách hoà bình, trung lập tích cực, luôn luôn ủng hộ cuộc đấu tranh giành độc lập của các dân tộc."
    },
    {
        "id": "p_35_3067",
        "question": "Ấn Độ theo đuổi chính sách hoà bình",
        "answer": "trung lập tích cực,",
        "context": "Về đối ngoại, Ấn Độ theo đuổi chính sách hoà bình, trung lập tích cực, luôn luôn ủng hộ cuộc đấu tranh giành độc lập của các dân tộc."
    },
    {
        "id": "p_35_3068",
        "question": "chính sách hoà bình ở Ấn Độ là gì",
        "answer": "trung lập tích cực,",
        "context": "Về đối ngoại, Ấn Độ theo đuổi chính sách hoà bình, trung lập tích cực, luôn luôn ủng hộ cuộc đấu tranh giành độc lập của các dân tộc."
    },
    {
        "id": "p_35_3069",
        "question": "Ấn Độ theo đuổi chính sách hoà bình như thế nào?",
        "answer": "trung lập tích cực,",
        "context": "Về đối ngoại, Ấn Độ theo đuổi chính sách hoà bình, trung lập tích cực, luôn luôn ủng hộ cuộc đấu tranh giành độc lập của các dân tộc."
    },
    {
        "id": "p_35_3070",
        "question": "Ấn Độ đã theo đuổi chính sách hoà bình nào",
        "answer": "trung lập tích cực,",
        "context": "Về đối ngoại, Ấn Độ theo đuổi chính sách hoà bình, trung lập tích cực, luôn luôn ủng hộ cuộc đấu tranh giành độc lập của các dân tộc."
    },
    {
        "id": "p_35_3071",
        "question": "khi nào Ấn Độ thiết lập quan hệ ngoài giao với Việt Nam",
        "answer": "Ngày 7 - 1 - 1972,",
        "context": "Ngày 7 - 1 - 1972, Ấn Độ chính thức thiết lập quan hệ ngoai giao với Việt Nam. 34"
    },
    {
        "id": "p_35_3072",
        "question": "khi nào Ấn Độ thiết lập quan hệ ngoại giao với Việt Nam",
        "answer": "Ngày 7 - 1 - 1972,",
        "context": "Ngày 7 - 1 - 1972, Ấn Độ chính thức thiết lập quan hệ ngoai giao với Việt Nam. 34"
    },
    {
        "id": "p_35_3073",
        "question": "khi nào Ấn Độ thiết lập quan hệ với Việt Nam",
        "answer": "Ngày 7 - 1 - 1972,",
        "context": "Ngày 7 - 1 - 1972, Ấn Độ chính thức thiết lập quan hệ ngoai giao với Việt Nam. 34"
    },
    {
        "id": "p_35_3074",
        "question": "khi nào Ấn Độ thiết lập quan hệ ngoài giao với Việt Nam?",
        "answer": "Ngày 7 - 1 - 1972,",
        "context": "Ngày 7 - 1 - 1972, Ấn Độ chính thức thiết lập quan hệ ngoai giao với Việt Nam. 34"
    },
    {
        "id": "p_35_3075",
        "question": "khi nào Ấn Độ thiết lập quan hệ ngoài giao với việt nam",
        "answer": "Ngày 7 - 1 - 1972,",
        "context": "Ngày 7 - 1 - 1972, Ấn Độ chính thức thiết lập quan hệ ngoai giao với Việt Nam. 34"
    },
    {
        "id": "p_35_3076",
        "question": "khi nào Ấn Độ thiết lập quan hệ ngoại giao với việt nam",
        "answer": "Ngày 7 - 1 - 1972,",
        "context": "Ngày 7 - 1 - 1972, Ấn Độ chính thức thiết lập quan hệ ngoai giao với Việt Nam. 34"
    },
    {
        "id": "p_35_3077",
        "question": "khi nào Ấn Độ chính thức thiết lập quan hệ ngoài giao với Việt Nam",
        "answer": "Ngày 7 - 1 - 1972,",
        "context": "Ngày 7 - 1 - 1972, Ấn Độ chính thức thiết lập quan hệ ngoai giao với Việt Nam. 34"
    },
    {
        "id": "p_35_3078",
        "question": "khi nào Ấn Độ thiết lập quan hệ ngoại giao với Việt Nam?",
        "answer": "Ngày 7 - 1 - 1972,",
        "context": "Ngày 7 - 1 - 1972, Ấn Độ chính thức thiết lập quan hệ ngoai giao với Việt Nam. 34"
    },
    {
        "id": "p_35_3079",
        "question": "khi nào Ấn Độ thiết lập quan hệ ngoài giao",
        "answer": "Ngày 7 - 1 - 1972,",
        "context": "Ngày 7 - 1 - 1972, Ấn Độ chính thức thiết lập quan hệ ngoai giao với Việt Nam. 34"
    },
    {
        "id": "p_35_3080",
        "question": "Ấn Độ chính thức thiết lập quan hệ ngoài giao với Việt Nam khi nào",
        "answer": "Ngày 7 - 1 - 1972,",
        "context": "Ngày 7 - 1 - 1972, Ấn Độ chính thức thiết lập quan hệ ngoai giao với Việt Nam. 34"
    }
]