[
    {
        "id": "p_17_1161",
        "question": "sự khủng hoảng của chế độ xã hội chủ nghĩa các nước Đông Âu là gì",
        "answer": "Cuộc khủng hoảng dẩu mỏ năm 1973",
        "context": "2 Sự khủng hoảng của chế độ xã hội chủ nghĩa các nước Đông Âu Cuộc khủng hoảng dẩu mỏ năm 1973 tác động manh đến nên kinh tế của các nước Đông Âu."
    },
    {
        "id": "p_17_1162",
        "question": "cuộc khủng hoảng dẩu mỏ năm 1973 ảnh hưởng như thế nào đến kinh tế của các nước Đông Âu",
        "answer": "tác động manh đến nên kinh tế của các nước Đông Âu.",
        "context": "2 Sự khủng hoảng của chế độ xã hội chủ nghĩa các nước Đông Âu Cuộc khủng hoảng dẩu mỏ năm 1973 tác động manh đến nên kinh tế của các nước Đông Âu."
    },
    {
        "id": "p_17_1163",
        "question": "cuộc khủng hoảng dẩu mỏ ảnh hưởng như thế nào đến kinh tế của các nước Đông Âu",
        "answer": "tác động manh đến nên kinh tế của các nước Đông Âu.",
        "context": "2 Sự khủng hoảng của chế độ xã hội chủ nghĩa các nước Đông Âu Cuộc khủng hoảng dẩu mỏ năm 1973 tác động manh đến nên kinh tế của các nước Đông Âu."
    },
    {
        "id": "p_17_1164",
        "question": "sự khủng hoảng của chế độ xã hội chủ nghĩa các nước Đông Âu",
        "answer": "Cuộc khủng hoảng dẩu mỏ năm 1973",
        "context": "2 Sự khủng hoảng của chế độ xã hội chủ nghĩa các nước Đông Âu Cuộc khủng hoảng dẩu mỏ năm 1973 tác động manh đến nên kinh tế của các nước Đông Âu."
    },
    {
        "id": "p_17_1165",
        "question": "cuộc khủng hoảng dẩu mỏ năm 1973 ảnh hưởng như thế nào đến chế độ xã hội chủ nghĩa các nước Đông Âu",
        "answer": "tác động manh đến nên kinh tế của các nước Đông Âu.",
        "context": "2 Sự khủng hoảng của chế độ xã hội chủ nghĩa các nước Đông Âu Cuộc khủng hoảng dẩu mỏ năm 1973 tác động manh đến nên kinh tế của các nước Đông Âu."
    },
    {
        "id": "p_17_1166",
        "question": "sự khủng hoảng của chế độ xã hội chủ nghĩa các nước Đông Âu là gì?",
        "answer": "Cuộc khủng hoảng dẩu mỏ năm 1973",
        "context": "2 Sự khủng hoảng của chế độ xã hội chủ nghĩa các nước Đông Âu Cuộc khủng hoảng dẩu mỏ năm 1973 tác động manh đến nên kinh tế của các nước Đông Âu."
    },
    {
        "id": "p_17_1167",
        "question": "cuộc khủng hoảng dẩu mỏ ảnh hưởng đến kinh tế của các nước Đông Âu như thế nào",
        "answer": "tác động manh đến nên kinh tế của các nước Đông Âu.",
        "context": "2 Sự khủng hoảng của chế độ xã hội chủ nghĩa các nước Đông Âu Cuộc khủng hoảng dẩu mỏ năm 1973 tác động manh đến nên kinh tế của các nước Đông Âu."
    },
    {
        "id": "p_17_1168",
        "question": "cuộc khủng hoảng dẩu mỏ đã ảnh hưởng đến kinh tế của các nước Đông Âu như thế nào",
        "answer": "tác động manh đến nên kinh tế của các nước Đông Âu.",
        "context": "2 Sự khủng hoảng của chế độ xã hội chủ nghĩa các nước Đông Âu Cuộc khủng hoảng dẩu mỏ năm 1973 tác động manh đến nên kinh tế của các nước Đông Âu."
    },
    {
        "id": "p_17_1169",
        "question": "cuộc khủng hoảng xã hội chủ nghĩa các nước Đông Âu ảnh hưởng như thế nào đến kinh tế của chúng ta",
        "answer": "tác động manh đến nên kinh tế của các nước Đông Âu.",
        "context": "2 Sự khủng hoảng của chế độ xã hội chủ nghĩa các nước Đông Âu Cuộc khủng hoảng dẩu mỏ năm 1973 tác động manh đến nên kinh tế của các nước Đông Âu."
    },
    {
        "id": "p_17_1170",
        "question": "cuộc khủng hoảng xã hội chủ nghĩa các nước Đông Âu ảnh hưởng như thế nào đến kinh tế",
        "answer": "tác động manh đến nên kinh tế của các nước Đông Âu.",
        "context": "2 Sự khủng hoảng của chế độ xã hội chủ nghĩa các nước Đông Âu Cuộc khủng hoảng dẩu mỏ năm 1973 tác động manh đến nên kinh tế của các nước Đông Âu."
    },
    {
        "id": "p_17_1171",
        "question": "nền kinh tế Đông Âu ảnh hưởng như thế nào đến lòng tin của nhân dân",
        "answer": "ngày càng giảm sút.",
        "context": "Vào những năm cuối của thập kỉ 70 - đẩu thập kỉ 80, nền kinh tế Đông Âu lâm vào tình trạng trì trệ. Lòng tin của nhân dân vào Đảng Cộng sản và Nhà nước ngày càng giảm sút."
    },
    {
        "id": "p_17_1172",
        "question": "nền kinh tế đông Âu ảnh hưởng như thế nào đến lòng tin của nhân dân",
        "answer": "ngày càng giảm sút.",
        "context": "Vào những năm cuối của thập kỉ 70 - đẩu thập kỉ 80, nền kinh tế Đông Âu lâm vào tình trạng trì trệ. Lòng tin của nhân dân vào Đảng Cộng sản và Nhà nước ngày càng giảm sút."
    },
    {
        "id": "p_17_1173",
        "question": "khi nào nền kinh tế Đông Âu lâm vào trì trệ",
        "answer": "năm cuối của thập kỉ 70 - đẩu thập kỉ 80,",
        "context": "Vào những năm cuối của thập kỉ 70 - đẩu thập kỉ 80, nền kinh tế Đông Âu lâm vào tình trạng trì trệ. Lòng tin của nhân dân vào Đảng Cộng sản và Nhà nước ngày càng giảm sút."
    },
    {
        "id": "p_17_1174",
        "question": "nền kinh tế Đông Âu bắt đầu như thế nào",
        "answer": "lâm vào tình trạng trì trệ.",
        "context": "Vào những năm cuối của thập kỉ 70 - đẩu thập kỉ 80, nền kinh tế Đông Âu lâm vào tình trạng trì trệ. Lòng tin của nhân dân vào Đảng Cộng sản và Nhà nước ngày càng giảm sút."
    },
    {
        "id": "p_17_1175",
        "question": "khi nào nền kinh tế Đông Âu trì trệ",
        "answer": "năm cuối của thập kỉ 70 - đẩu thập kỉ 80,",
        "context": "Vào những năm cuối của thập kỉ 70 - đẩu thập kỉ 80, nền kinh tế Đông Âu lâm vào tình trạng trì trệ. Lòng tin của nhân dân vào Đảng Cộng sản và Nhà nước ngày càng giảm sút."
    },
    {
        "id": "p_17_1176",
        "question": "nền kinh tế Đông Âu ảnh hưởng đến lòng tin của nhân dân như thế nào",
        "answer": "ngày càng giảm sút.",
        "context": "Vào những năm cuối của thập kỉ 70 - đẩu thập kỉ 80, nền kinh tế Đông Âu lâm vào tình trạng trì trệ. Lòng tin của nhân dân vào Đảng Cộng sản và Nhà nước ngày càng giảm sút."
    },
    {
        "id": "p_17_1177",
        "question": "nền kinh tế Đông Âu ảnh hưởng như thế nào đến sự trì trệ",
        "answer": "Lòng tin của nhân dân vào Đảng Cộng sản và Nhà nước",
        "context": "Vào những năm cuối của thập kỉ 70 - đẩu thập kỉ 80, nền kinh tế Đông Âu lâm vào tình trạng trì trệ. Lòng tin của nhân dân vào Đảng Cộng sản và Nhà nước ngày càng giảm sút."
    },
    {
        "id": "p_17_1178",
        "question": "khi nào nền kinh tế đông Âu lâm vào trì trệ",
        "answer": "năm cuối của thập kỉ 70 - đẩu thập kỉ 80,",
        "context": "Vào những năm cuối của thập kỉ 70 - đẩu thập kỉ 80, nền kinh tế Đông Âu lâm vào tình trạng trì trệ. Lòng tin của nhân dân vào Đảng Cộng sản và Nhà nước ngày càng giảm sút."
    },
    {
        "id": "p_17_1179",
        "question": "khi nào nền kinh tế đông Âu trì trệ",
        "answer": "năm cuối của thập kỉ 70 - đẩu thập kỉ 80,",
        "context": "Vào những năm cuối của thập kỉ 70 - đẩu thập kỉ 80, nền kinh tế Đông Âu lâm vào tình trạng trì trệ. Lòng tin của nhân dân vào Đảng Cộng sản và Nhà nước ngày càng giảm sút."
    },
    {
        "id": "p_17_1180",
        "question": "nền kinh tế đông Âu ảnh hưởng như thế nào đến sự trì trệ",
        "answer": "ngày càng giảm sút.",
        "context": "Vào những năm cuối của thập kỉ 70 - đẩu thập kỉ 80, nền kinh tế Đông Âu lâm vào tình trạng trì trệ. Lòng tin của nhân dân vào Đảng Cộng sản và Nhà nước ngày càng giảm sút."
    },
    {
        "id": "p_17_1181",
        "question": "điều gì đã gây ra cuộc khủng hoảng ở các nước xã hội chủ nghĩa Đông Âu",
        "answer": "hoat động phá hoại của các thế lực phản động",
        "context": "Ban lãnh đao Đảng và Nhà nước ở các nước Đông Âu đã có những cố gắng để điêu chỉnh sự phát triển kinh tế Nhưng sai lẩm của những biện pháp cải cách cộng với sự bế tắc trong công cuộc cải tổ ở Liên Xô và hoat động phá hoại của các thế lực phản động đã làm cho cuộc khủng hoảng ở các nước xã hội chủ nghĩa Đông Âu ngày càng gay gắt."
    },
    {
        "id": "p_17_1182",
        "question": "điều gì đã gây ra cuộc khủng hoảng xã hội chủ nghĩa Đông Âu",
        "answer": "hoat động phá hoại của các thế lực phản động",
        "context": "Ban lãnh đao Đảng và Nhà nước ở các nước Đông Âu đã có những cố gắng để điêu chỉnh sự phát triển kinh tế Nhưng sai lẩm của những biện pháp cải cách cộng với sự bế tắc trong công cuộc cải tổ ở Liên Xô và hoat động phá hoại của các thế lực phản động đã làm cho cuộc khủng hoảng ở các nước xã hội chủ nghĩa Đông Âu ngày càng gay gắt."
    },
    {
        "id": "p_17_1183",
        "question": "điều gì đã gây ra khủng hoảng xã hội chủ nghĩa Đông Âu",
        "answer": "hoat động phá hoại của các thế lực phản động",
        "context": "Ban lãnh đao Đảng và Nhà nước ở các nước Đông Âu đã có những cố gắng để điêu chỉnh sự phát triển kinh tế Nhưng sai lẩm của những biện pháp cải cách cộng với sự bế tắc trong công cuộc cải tổ ở Liên Xô và hoat động phá hoại của các thế lực phản động đã làm cho cuộc khủng hoảng ở các nước xã hội chủ nghĩa Đông Âu ngày càng gay gắt."
    },
    {
        "id": "p_17_1184",
        "question": "điều gì đã gây ra cuộc khủng hoảng ở các nước Đông Âu",
        "answer": "hoat động phá hoại của các thế lực phản động",
        "context": "Ban lãnh đao Đảng và Nhà nước ở các nước Đông Âu đã có những cố gắng để điêu chỉnh sự phát triển kinh tế Nhưng sai lẩm của những biện pháp cải cách cộng với sự bế tắc trong công cuộc cải tổ ở Liên Xô và hoat động phá hoại của các thế lực phản động đã làm cho cuộc khủng hoảng ở các nước xã hội chủ nghĩa Đông Âu ngày càng gay gắt."
    },
    {
        "id": "p_17_1185",
        "question": "điều gì đã gây ra cuộc khủng hoảng ở các nước xã hội chủ nghĩa Đông Âu?",
        "answer": "hoat động phá hoại của các thế lực phản động",
        "context": "Ban lãnh đao Đảng và Nhà nước ở các nước Đông Âu đã có những cố gắng để điêu chỉnh sự phát triển kinh tế Nhưng sai lẩm của những biện pháp cải cách cộng với sự bế tắc trong công cuộc cải tổ ở Liên Xô và hoat động phá hoại của các thế lực phản động đã làm cho cuộc khủng hoảng ở các nước xã hội chủ nghĩa Đông Âu ngày càng gay gắt."
    },
    {
        "id": "p_17_1186",
        "question": "những gì đã xảy ra trong cuộc khủng hoảng ở các nước Đông Âu",
        "answer": "hoat động phá hoại của các thế lực phản động",
        "context": "Ban lãnh đao Đảng và Nhà nước ở các nước Đông Âu đã có những cố gắng để điêu chỉnh sự phát triển kinh tế Nhưng sai lẩm của những biện pháp cải cách cộng với sự bế tắc trong công cuộc cải tổ ở Liên Xô và hoat động phá hoại của các thế lực phản động đã làm cho cuộc khủng hoảng ở các nước xã hội chủ nghĩa Đông Âu ngày càng gay gắt."
    },
    {
        "id": "p_17_1187",
        "question": "điều gì đã gây ra cuộc khủng hoảng xã hội chủ nghĩa Đông Âu?",
        "answer": "hoat động phá hoại của các thế lực phản động",
        "context": "Ban lãnh đao Đảng và Nhà nước ở các nước Đông Âu đã có những cố gắng để điêu chỉnh sự phát triển kinh tế Nhưng sai lẩm của những biện pháp cải cách cộng với sự bế tắc trong công cuộc cải tổ ở Liên Xô và hoat động phá hoại của các thế lực phản động đã làm cho cuộc khủng hoảng ở các nước xã hội chủ nghĩa Đông Âu ngày càng gay gắt."
    },
    {
        "id": "p_17_1188",
        "question": "điều gì đã gây ra cuộc khủng hoảng ở các nước xã hội chủ nghĩa đông Âu",
        "answer": "hoat động phá hoại của các thế lực phản động",
        "context": "Ban lãnh đao Đảng và Nhà nước ở các nước Đông Âu đã có những cố gắng để điêu chỉnh sự phát triển kinh tế Nhưng sai lẩm của những biện pháp cải cách cộng với sự bế tắc trong công cuộc cải tổ ở Liên Xô và hoat động phá hoại của các thế lực phản động đã làm cho cuộc khủng hoảng ở các nước xã hội chủ nghĩa Đông Âu ngày càng gay gắt."
    },
    {
        "id": "p_17_1189",
        "question": "điều gì đã xảy ra trong cuộc khủng hoảng ở các nước Đông Âu",
        "answer": "hoat động phá hoại của các thế lực phản động",
        "context": "Ban lãnh đao Đảng và Nhà nước ở các nước Đông Âu đã có những cố gắng để điêu chỉnh sự phát triển kinh tế Nhưng sai lẩm của những biện pháp cải cách cộng với sự bế tắc trong công cuộc cải tổ ở Liên Xô và hoat động phá hoại của các thế lực phản động đã làm cho cuộc khủng hoảng ở các nước xã hội chủ nghĩa Đông Âu ngày càng gay gắt."
    },
    {
        "id": "p_17_1190",
        "question": "những gì đã gây ra cuộc khủng hoảng ở các nước Đông Âu",
        "answer": "hoat động phá hoại của các thế lực phản động",
        "context": "Ban lãnh đao Đảng và Nhà nước ở các nước Đông Âu đã có những cố gắng để điêu chỉnh sự phát triển kinh tế Nhưng sai lẩm của những biện pháp cải cách cộng với sự bế tắc trong công cuộc cải tổ ở Liên Xô và hoat động phá hoại của các thế lực phản động đã làm cho cuộc khủng hoảng ở các nước xã hội chủ nghĩa Đông Âu ngày càng gay gắt."
    },
    {
        "id": "p_17_1191",
        "question": "định nghĩa ban lãnh đạo đông Âu",
        "answer": "từ bỏ quyên lãnh đạo của Đảng.",
        "context": "Ban lãnh đạo ở các nước Đông Âu lẩn lượt từ bỏ quyên lãnh đạo của Đảng. chấp nhận chế độ đa nguyên; đa đảng và tiến hành tổng tuyển cử, chấm dứt chế độ xã hội chủ nghĩa."
    },
    {
        "id": "p_17_1192",
        "question": "định nghĩa ban lãnh đạo ở các nước Đông Âu",
        "answer": "từ bỏ quyên lãnh đạo của Đảng.",
        "context": "Ban lãnh đạo ở các nước Đông Âu lẩn lượt từ bỏ quyên lãnh đạo của Đảng. chấp nhận chế độ đa nguyên; đa đảng và tiến hành tổng tuyển cử, chấm dứt chế độ xã hội chủ nghĩa."
    },
    {
        "id": "p_17_1193",
        "question": "định nghĩa của ban lãnh đạo ở các nước Đông Âu",
        "answer": "từ bỏ quyên lãnh đạo của Đảng.",
        "context": "Ban lãnh đạo ở các nước Đông Âu lẩn lượt từ bỏ quyên lãnh đạo của Đảng. chấp nhận chế độ đa nguyên; đa đảng và tiến hành tổng tuyển cử, chấm dứt chế độ xã hội chủ nghĩa."
    },
    {
        "id": "p_17_1194",
        "question": "định nghĩa ban lãnh đạo ở Đông Âu",
        "answer": "từ bỏ quyên lãnh đạo của Đảng.",
        "context": "Ban lãnh đạo ở các nước Đông Âu lẩn lượt từ bỏ quyên lãnh đạo của Đảng. chấp nhận chế độ đa nguyên; đa đảng và tiến hành tổng tuyển cử, chấm dứt chế độ xã hội chủ nghĩa."
    },
    {
        "id": "p_17_1195",
        "question": "định nghĩa của ban lãnh đạo ở các nước Đông Âu là gì",
        "answer": "từ bỏ quyên lãnh đạo của Đảng.",
        "context": "Ban lãnh đạo ở các nước Đông Âu lẩn lượt từ bỏ quyên lãnh đạo của Đảng. chấp nhận chế độ đa nguyên; đa đảng và tiến hành tổng tuyển cử, chấm dứt chế độ xã hội chủ nghĩa."
    },
    {
        "id": "p_17_1196",
        "question": "định nghĩa của ban lãnh đạo ở Đông Âu",
        "answer": "từ bỏ quyên lãnh đạo của Đảng.",
        "context": "Ban lãnh đạo ở các nước Đông Âu lẩn lượt từ bỏ quyên lãnh đạo của Đảng. chấp nhận chế độ đa nguyên; đa đảng và tiến hành tổng tuyển cử, chấm dứt chế độ xã hội chủ nghĩa."
    },
    {
        "id": "p_17_1197",
        "question": "định nghĩa ban lãnh đạo Đông Âu",
        "answer": "từ bỏ quyên lãnh đạo của Đảng.",
        "context": "Ban lãnh đạo ở các nước Đông Âu lẩn lượt từ bỏ quyên lãnh đạo của Đảng. chấp nhận chế độ đa nguyên; đa đảng và tiến hành tổng tuyển cử, chấm dứt chế độ xã hội chủ nghĩa."
    },
    {
        "id": "p_17_1198",
        "question": "định nghĩa của ban lãnh đạo ở Đông Âu là gì",
        "answer": "từ bỏ quyên lãnh đạo của Đảng.",
        "context": "Ban lãnh đạo ở các nước Đông Âu lẩn lượt từ bỏ quyên lãnh đạo của Đảng. chấp nhận chế độ đa nguyên; đa đảng và tiến hành tổng tuyển cử, chấm dứt chế độ xã hội chủ nghĩa."
    },
    {
        "id": "p_17_1199",
        "question": "định nghĩa lãnh đạo đông Âu",
        "answer": "từ bỏ quyên lãnh đạo của Đảng.",
        "context": "Ban lãnh đạo ở các nước Đông Âu lẩn lượt từ bỏ quyên lãnh đạo của Đảng. chấp nhận chế độ đa nguyên; đa đảng và tiến hành tổng tuyển cử, chấm dứt chế độ xã hội chủ nghĩa."
    },
    {
        "id": "p_17_1200",
        "question": "định nghĩa của ban lãnh đạo ở các nước đông Âu",
        "answer": "từ bỏ quyên lãnh đạo của Đảng.",
        "context": "Ban lãnh đạo ở các nước Đông Âu lẩn lượt từ bỏ quyên lãnh đạo của Đảng. chấp nhận chế độ đa nguyên; đa đảng và tiến hành tổng tuyển cử, chấm dứt chế độ xã hội chủ nghĩa."
    },
    {
        "id": "p_17_1201",
        "question": "các nước Đông Âu từ bỏ chủ nghĩa xã hội",
        "answer": "\"bức tường Béclin\" bị phá bỏ.",
        "context": "Các nước Đông Âu lẩn lượt từ bỏ chủ nghĩa xã hội_ U Culig Ilud Dal Cllu DuC, CuuC NlunIS Iludnlg oullg IlU lU CUOI Ildll 1909 IllnicU Ii2UUI từ Đông Đức chạy sang Tây Đức, \"bức tường Béclin\" bị phá bỏ."
    },
    {
        "id": "p_17_1202",
        "question": "những nước nào từ bỏ chủ nghĩa xã hội",
        "answer": "Các nước Đông Âu",
        "context": "Các nước Đông Âu lẩn lượt từ bỏ chủ nghĩa xã hội_ U Culig Ilud Dal Cllu DuC, CuuC NlunIS Iludnlg oullg IlU lU CUOI Ildll 1909 IllnicU Ii2UUI từ Đông Đức chạy sang Tây Đức, \"bức tường Béclin\" bị phá bỏ."
    },
    {
        "id": "p_17_1203",
        "question": "tại sao các nước Đông Âu lại phá bỏ chủ nghĩa xã hội",
        "answer": "\"bức tường Béclin\" bị phá bỏ.",
        "context": "Các nước Đông Âu lẩn lượt từ bỏ chủ nghĩa xã hội_ U Culig Ilud Dal Cllu DuC, CuuC NlunIS Iludnlg oullg IlU lU CUOI Ildll 1909 IllnicU Ii2UUI từ Đông Đức chạy sang Tây Đức, \"bức tường Béclin\" bị phá bỏ."
    },
    {
        "id": "p_17_1204",
        "question": "các nước Đông Âu từ bỏ chủ nghĩa xã hội như thế nào",
        "answer": "\"bức tường Béclin\" bị phá bỏ.",
        "context": "Các nước Đông Âu lẩn lượt từ bỏ chủ nghĩa xã hội_ U Culig Ilud Dal Cllu DuC, CuuC NlunIS Iludnlg oullg IlU lU CUOI Ildll 1909 IllnicU Ii2UUI từ Đông Đức chạy sang Tây Đức, \"bức tường Béclin\" bị phá bỏ."
    },
    {
        "id": "p_17_1205",
        "question": "các nước Đông Âu từ bỏ chủ nghĩa xã hội là gì",
        "answer": "\"bức tường Béclin\" bị phá bỏ.",
        "context": "Các nước Đông Âu lẩn lượt từ bỏ chủ nghĩa xã hội_ U Culig Ilud Dal Cllu DuC, CuuC NlunIS Iludnlg oullg IlU lU CUOI Ildll 1909 IllnicU Ii2UUI từ Đông Đức chạy sang Tây Đức, \"bức tường Béclin\" bị phá bỏ."
    },
    {
        "id": "p_17_1206",
        "question": "các nước Đông Âu từ bỏ chủ nghĩa xã hội như thế nào?",
        "answer": "\"bức tường Béclin\" bị phá bỏ.",
        "context": "Các nước Đông Âu lẩn lượt từ bỏ chủ nghĩa xã hội_ U Culig Ilud Dal Cllu DuC, CuuC NlunIS Iludnlg oullg IlU lU CUOI Ildll 1909 IllnicU Ii2UUI từ Đông Đức chạy sang Tây Đức, \"bức tường Béclin\" bị phá bỏ."
    },
    {
        "id": "p_17_1207",
        "question": "những nước nào từ bỏ chủ nghĩa xã hội?",
        "answer": "Các nước Đông Âu",
        "context": "Các nước Đông Âu lẩn lượt từ bỏ chủ nghĩa xã hội_ U Culig Ilud Dal Cllu DuC, CuuC NlunIS Iludnlg oullg IlU lU CUOI Ildll 1909 IllnicU Ii2UUI từ Đông Đức chạy sang Tây Đức, \"bức tường Béclin\" bị phá bỏ."
    },
    {
        "id": "p_17_1208",
        "question": "chủ nghĩa xã hội bị phá bỏ ở đâu",
        "answer": "\"bức tường Béclin\"",
        "context": "Các nước Đông Âu lẩn lượt từ bỏ chủ nghĩa xã hội_ U Culig Ilud Dal Cllu DuC, CuuC NlunIS Iludnlg oullg IlU lU CUOI Ildll 1909 IllnicU Ii2UUI từ Đông Đức chạy sang Tây Đức, \"bức tường Béclin\" bị phá bỏ."
    },
    {
        "id": "p_17_1209",
        "question": "tại sao các nước Đông Âu lại phá bỏ chủ nghĩa xã hội?",
        "answer": "\"bức tường Béclin\"",
        "context": "Các nước Đông Âu lẩn lượt từ bỏ chủ nghĩa xã hội_ U Culig Ilud Dal Cllu DuC, CuuC NlunIS Iludnlg oullg IlU lU CUOI Ildll 1909 IllnicU Ii2UUI từ Đông Đức chạy sang Tây Đức, \"bức tường Béclin\" bị phá bỏ."
    },
    {
        "id": "p_17_1210",
        "question": "chủ nghĩa xã hội được phá bỏ ở đâu",
        "answer": "\"bức tường Béclin\"",
        "context": "Các nước Đông Âu lẩn lượt từ bỏ chủ nghĩa xã hội_ U Culig Ilud Dal Cllu DuC, CuuC NlunIS Iludnlg oullg IlU lU CUOI Ildll 1909 IllnicU Ii2UUI từ Đông Đức chạy sang Tây Đức, \"bức tường Béclin\" bị phá bỏ."
    },
    {
        "id": "p_17_1211",
        "question": "bức tường béclin bị phả bỏ khi nào",
        "answer": "Ngày 3 - 10 1990,",
        "context": "Ngày 3 - 10 1990, việc thống nhất nước Đức đã được thực hiện với sự sáp nhập Cộng hoà Dân chủ Đức vào Cộng hoà Liên bang Đức . Hình 6. \"Bức tường Béclin\" bị phả bỏ 16"
    },
    {
        "id": "p_17_1212",
        "question": "những gì đã xảy ra trong việc thống nhất nước Đức",
        "answer": "sự sáp nhập Cộng hoà Dân chủ Đức",
        "context": "Ngày 3 - 10 1990, việc thống nhất nước Đức đã được thực hiện với sự sáp nhập Cộng hoà Dân chủ Đức vào Cộng hoà Liên bang Đức . Hình 6. \"Bức tường Béclin\" bị phả bỏ 16"
    },
    {
        "id": "p_17_1213",
        "question": "bức tường béclin bị phả bỏ vào năm nào",
        "answer": "1990,",
        "context": "Ngày 3 - 10 1990, việc thống nhất nước Đức đã được thực hiện với sự sáp nhập Cộng hoà Dân chủ Đức vào Cộng hoà Liên bang Đức . Hình 6. \"Bức tường Béclin\" bị phả bỏ 16"
    },
    {
        "id": "p_17_1214",
        "question": "những gì đã xảy ra trong cuộc thống nhất nước Đức",
        "answer": "sự sáp nhập Cộng hoà Dân chủ Đức",
        "context": "Ngày 3 - 10 1990, việc thống nhất nước Đức đã được thực hiện với sự sáp nhập Cộng hoà Dân chủ Đức vào Cộng hoà Liên bang Đức . Hình 6. \"Bức tường Béclin\" bị phả bỏ 16"
    },
    {
        "id": "p_17_1215",
        "question": "bức tường béclin bị phả bỏ vào ngày nào",
        "answer": "Ngày 3 - 10 1990,",
        "context": "Ngày 3 - 10 1990, việc thống nhất nước Đức đã được thực hiện với sự sáp nhập Cộng hoà Dân chủ Đức vào Cộng hoà Liên bang Đức . Hình 6. \"Bức tường Béclin\" bị phả bỏ 16"
    },
    {
        "id": "p_17_1216",
        "question": "khi nào thống nhất nước Đức được thực hiện",
        "answer": "Ngày 3 - 10 1990,",
        "context": "Ngày 3 - 10 1990, việc thống nhất nước Đức đã được thực hiện với sự sáp nhập Cộng hoà Dân chủ Đức vào Cộng hoà Liên bang Đức . Hình 6. \"Bức tường Béclin\" bị phả bỏ 16"
    },
    {
        "id": "p_17_1217",
        "question": "những gì đã xảy ra trong sự thống nhất của nước Đức",
        "answer": "sự sáp nhập Cộng hoà Dân chủ Đức",
        "context": "Ngày 3 - 10 1990, việc thống nhất nước Đức đã được thực hiện với sự sáp nhập Cộng hoà Dân chủ Đức vào Cộng hoà Liên bang Đức . Hình 6. \"Bức tường Béclin\" bị phả bỏ 16"
    },
    {
        "id": "p_17_1218",
        "question": "khi nào nước Đức được thống nhất",
        "answer": "Ngày 3 - 10 1990,",
        "context": "Ngày 3 - 10 1990, việc thống nhất nước Đức đã được thực hiện với sự sáp nhập Cộng hoà Dân chủ Đức vào Cộng hoà Liên bang Đức . Hình 6. \"Bức tường Béclin\" bị phả bỏ 16"
    },
    {
        "id": "p_17_1219",
        "question": "những gì đã xảy ra trong sự thống nhất nước Đức",
        "answer": "sự sáp nhập Cộng hoà Dân chủ Đức",
        "context": "Ngày 3 - 10 1990, việc thống nhất nước Đức đã được thực hiện với sự sáp nhập Cộng hoà Dân chủ Đức vào Cộng hoà Liên bang Đức . Hình 6. \"Bức tường Béclin\" bị phả bỏ 16"
    },
    {
        "id": "p_17_1220",
        "question": "những gì đã xảy ra trong cuộc thống nhất của nước Đức",
        "answer": "sự sáp nhập Cộng hoà Dân chủ Đức",
        "context": "Ngày 3 - 10 1990, việc thống nhất nước Đức đã được thực hiện với sự sáp nhập Cộng hoà Dân chủ Đức vào Cộng hoà Liên bang Đức . Hình 6. \"Bức tường Béclin\" bị phả bỏ 16"
    }
]