[
    {
        "id": "p_31_2561",
        "question": "điều gì đã gây ra khủng hoảng tài chính ở aSEAN",
        "answer": "Nển kinh tế bị suy thoái,",
        "context": "Năm 1997 1998 , các nước ASEAN trải qua một cuộc khủng hoảng tài chính nghiêm trọng. Nển kinh tế bị suy thoái, tình hình chính trị một số nước không ổn định."
    },
    {
        "id": "p_31_2562",
        "question": "cuộc khủng hoảng tài chính ở aSEAN là khi nào",
        "answer": "Năm 1997 1998",
        "context": "Năm 1997 1998 , các nước ASEAN trải qua một cuộc khủng hoảng tài chính nghiêm trọng. Nển kinh tế bị suy thoái, tình hình chính trị một số nước không ổn định."
    },
    {
        "id": "p_31_2563",
        "question": "cuộc khủng hoảng tài chính ở aSEAN là gì",
        "answer": "Nển kinh tế bị suy thoái,",
        "context": "Năm 1997 1998 , các nước ASEAN trải qua một cuộc khủng hoảng tài chính nghiêm trọng. Nển kinh tế bị suy thoái, tình hình chính trị một số nước không ổn định."
    },
    {
        "id": "p_31_2564",
        "question": "cuộc khủng hoảng tài chính của aSEAN là khi nào",
        "answer": "Năm 1997 1998",
        "context": "Năm 1997 1998 , các nước ASEAN trải qua một cuộc khủng hoảng tài chính nghiêm trọng. Nển kinh tế bị suy thoái, tình hình chính trị một số nước không ổn định."
    },
    {
        "id": "p_31_2565",
        "question": "cuộc khủng hoảng tài chính của aSEAN là gì",
        "answer": "Nển kinh tế bị suy thoái,",
        "context": "Năm 1997 1998 , các nước ASEAN trải qua một cuộc khủng hoảng tài chính nghiêm trọng. Nển kinh tế bị suy thoái, tình hình chính trị một số nước không ổn định."
    },
    {
        "id": "p_31_2566",
        "question": "khủng hoảng tài chính ở aSEAN là gì",
        "answer": "Nển kinh tế bị suy thoái,",
        "context": "Năm 1997 1998 , các nước ASEAN trải qua một cuộc khủng hoảng tài chính nghiêm trọng. Nển kinh tế bị suy thoái, tình hình chính trị một số nước không ổn định."
    },
    {
        "id": "p_31_2567",
        "question": "cuộc khủng hoảng tài chính nào đã xảy ra ở aSEAN",
        "answer": "cuộc khủng hoảng tài chính nghiêm trọng.",
        "context": "Năm 1997 1998 , các nước ASEAN trải qua một cuộc khủng hoảng tài chính nghiêm trọng. Nển kinh tế bị suy thoái, tình hình chính trị một số nước không ổn định."
    },
    {
        "id": "p_31_2568",
        "question": "cuộc khủng hoảng tài chính của các nước aSEAN là khi nào",
        "answer": "Năm 1997 1998",
        "context": "Năm 1997 1998 , các nước ASEAN trải qua một cuộc khủng hoảng tài chính nghiêm trọng. Nển kinh tế bị suy thoái, tình hình chính trị một số nước không ổn định."
    },
    {
        "id": "p_31_2569",
        "question": "cuộc khủng hoảng tài chính ở ASEAN là khi nào",
        "answer": "Năm 1997 1998",
        "context": "Năm 1997 1998 , các nước ASEAN trải qua một cuộc khủng hoảng tài chính nghiêm trọng. Nển kinh tế bị suy thoái, tình hình chính trị một số nước không ổn định."
    },
    {
        "id": "p_31_2570",
        "question": "khủng hoảng tài chính ở aSEAN là khi nào",
        "answer": "Năm 1997 1998",
        "context": "Năm 1997 1998 , các nước ASEAN trải qua một cuộc khủng hoảng tài chính nghiêm trọng. Nển kinh tế bị suy thoái, tình hình chính trị một số nước không ổn định."
    },
    {
        "id": "p_31_2571",
        "question": "các tiểu bang thống nhất phát triển như thế nào",
        "answer": "các nước ASEAN lại tiếp tục phát triển.",
        "context": "Sau vài năm khắc phuc, kinh tế dẩn dẩn được phục hổi , các nước ASEAN lại tiếp tục phát triển."
    },
    {
        "id": "p_31_2572",
        "question": "tại sao các nước aSEAN lại phát triển",
        "answer": "kinh tế dẩn dẩn được phục hổi",
        "context": "Sau vài năm khắc phuc, kinh tế dẩn dẩn được phục hổi , các nước ASEAN lại tiếp tục phát triển."
    },
    {
        "id": "p_31_2573",
        "question": "kinh tế của aSEAN là gì",
        "answer": "kinh tế dẩn dẩn được phục hổi",
        "context": "Sau vài năm khắc phuc, kinh tế dẩn dẩn được phục hổi , các nước ASEAN lại tiếp tục phát triển."
    },
    {
        "id": "p_31_2574",
        "question": "kinh tế của aSEAN được phục hổi như thế nào",
        "answer": "kinh tế dẩn dẩn được phục hổi",
        "context": "Sau vài năm khắc phuc, kinh tế dẩn dẩn được phục hổi , các nước ASEAN lại tiếp tục phát triển."
    },
    {
        "id": "p_31_2575",
        "question": "kinh tế ở aSEAN là gì",
        "answer": "kinh tế dẩn dẩn được phục hổi",
        "context": "Sau vài năm khắc phuc, kinh tế dẩn dẩn được phục hổi , các nước ASEAN lại tiếp tục phát triển."
    },
    {
        "id": "p_31_2576",
        "question": "các tiểu bang thống nhất phát triển như thế nào?",
        "answer": "các nước ASEAN lại tiếp tục phát triển.",
        "context": "Sau vài năm khắc phuc, kinh tế dẩn dẩn được phục hổi , các nước ASEAN lại tiếp tục phát triển."
    },
    {
        "id": "p_31_2577",
        "question": "kinh tế của các nước aSEAN là gì",
        "answer": "kinh tế dẩn dẩn được phục hổi",
        "context": "Sau vài năm khắc phuc, kinh tế dẩn dẩn được phục hổi , các nước ASEAN lại tiếp tục phát triển."
    },
    {
        "id": "p_31_2578",
        "question": "kinh tế của aSEAN như thế nào",
        "answer": "kinh tế dẩn dẩn được phục hổi",
        "context": "Sau vài năm khắc phuc, kinh tế dẩn dẩn được phục hổi , các nước ASEAN lại tiếp tục phát triển."
    },
    {
        "id": "p_31_2579",
        "question": "kinh tế của aSEAN được phục hổi như thế nào?",
        "answer": "các nước ASEAN lại tiếp tục phát triển.",
        "context": "Sau vài năm khắc phuc, kinh tế dẩn dẩn được phục hổi , các nước ASEAN lại tiếp tục phát triển."
    },
    {
        "id": "p_31_2580",
        "question": "các quốc gia thống nhất có kinh tế như thế nào",
        "answer": "các nước ASEAN lại tiếp tục phát triển.",
        "context": "Sau vài năm khắc phuc, kinh tế dẩn dẩn được phục hổi , các nước ASEAN lại tiếp tục phát triển."
    },
    {
        "id": "p_31_2581",
        "question": "xác định các nước đông dương",
        "answer": "Nhóm các nước Đông Dương",
        "context": "b) Nhóm các nước Đông Dương Sau khi giành được độc lập; về cơ bản các nước Đông Dương( 1) đã phát triển theo hướng kinh tế tập trung; đạt được một số thành tựu, nhưng còn nhiều khó khăn."
    },
    {
        "id": "p_31_2582",
        "question": "xác định các nước Đông Dương",
        "answer": "Sau khi giành được độc lập;",
        "context": "b) Nhóm các nước Đông Dương Sau khi giành được độc lập; về cơ bản các nước Đông Dương( 1) đã phát triển theo hướng kinh tế tập trung; đạt được một số thành tựu, nhưng còn nhiều khó khăn."
    },
    {
        "id": "p_31_2583",
        "question": "định nghĩa của các nước Đông Dương",
        "answer": "theo hướng kinh tế tập trung;",
        "context": "b) Nhóm các nước Đông Dương Sau khi giành được độc lập; về cơ bản các nước Đông Dương( 1) đã phát triển theo hướng kinh tế tập trung; đạt được một số thành tựu, nhưng còn nhiều khó khăn."
    },
    {
        "id": "p_31_2584",
        "question": "định nghĩa của các nước đông dương",
        "answer": "theo hướng kinh tế tập trung;",
        "context": "b) Nhóm các nước Đông Dương Sau khi giành được độc lập; về cơ bản các nước Đông Dương( 1) đã phát triển theo hướng kinh tế tập trung; đạt được một số thành tựu, nhưng còn nhiều khó khăn."
    },
    {
        "id": "p_31_2585",
        "question": "định nghĩa về các nước Đông Dương",
        "answer": "các nước Đông Dương( 1) đã phát triển theo hướng kinh tế tập trung;",
        "context": "b) Nhóm các nước Đông Dương Sau khi giành được độc lập; về cơ bản các nước Đông Dương( 1) đã phát triển theo hướng kinh tế tập trung; đạt được một số thành tựu, nhưng còn nhiều khó khăn."
    },
    {
        "id": "p_31_2586",
        "question": "định nghĩa về các nước đông dương",
        "answer": "các nước Đông Dương( 1) đã phát triển theo hướng kinh tế tập trung;",
        "context": "b) Nhóm các nước Đông Dương Sau khi giành được độc lập; về cơ bản các nước Đông Dương( 1) đã phát triển theo hướng kinh tế tập trung; đạt được một số thành tựu, nhưng còn nhiều khó khăn."
    },
    {
        "id": "p_31_2587",
        "question": "xác định nhóm các nước Đông Dương",
        "answer": "Sau khi giành được độc lập;",
        "context": "b) Nhóm các nước Đông Dương Sau khi giành được độc lập; về cơ bản các nước Đông Dương( 1) đã phát triển theo hướng kinh tế tập trung; đạt được một số thành tựu, nhưng còn nhiều khó khăn."
    },
    {
        "id": "p_31_2588",
        "question": "định nghĩa các nước Đông Dương",
        "answer": "theo hướng kinh tế tập trung;",
        "context": "b) Nhóm các nước Đông Dương Sau khi giành được độc lập; về cơ bản các nước Đông Dương( 1) đã phát triển theo hướng kinh tế tập trung; đạt được một số thành tựu, nhưng còn nhiều khó khăn."
    },
    {
        "id": "p_31_2589",
        "question": "định nghĩa các nước đông dương",
        "answer": "phát triển theo hướng kinh tế tập trung;",
        "context": "b) Nhóm các nước Đông Dương Sau khi giành được độc lập; về cơ bản các nước Đông Dương( 1) đã phát triển theo hướng kinh tế tập trung; đạt được một số thành tựu, nhưng còn nhiều khó khăn."
    },
    {
        "id": "p_31_2590",
        "question": "định nghĩa của các nước đông dương là gì",
        "answer": "kinh tế tập trung;",
        "context": "b) Nhóm các nước Đông Dương Sau khi giành được độc lập; về cơ bản các nước Đông Dương( 1) đã phát triển theo hướng kinh tế tập trung; đạt được một số thành tựu, nhưng còn nhiều khó khăn."
    },
    {
        "id": "p_31_2591",
        "question": "tại sao Campuchia lại là một nước nông nghiệp lạc hậu",
        "answer": "Bước vào thời kì hoà bình xây dựng đất nước,",
        "context": "Vào những năm 80 90 của thế kỉ XX, các nước này từng bước chuyển sang nên kinh tế thị trường Bước vào thời kì hoà bình xây dựng đất nước, nhân dân Lào đã đạt được một số thành tựu bước đẩu, nhưng về căn bản, Lào vẫn là một nước nông nghiệp lạc hậu: Từ cuối năm 1986, nước Lào thực hiện công cuộc đổi mới, nền kinh tế có sự khởi SdC , UUl S0llg CaC Uì [@C UuoC Cdl lmnlcl: UDI Ildll ZuUU lang J,/ 0, Sdll Xudl Ilong nghiệp tăng 4,59 , công nghiệp tăng 9,29 Sau khi tình hình chính trị ổn định, Campuchia bước vào thời kì phục hổi kinh tế và đạt được một số thành tựu đáng kể."
    },
    {
        "id": "p_31_2592",
        "question": "nền kinh tế của nước Lào là gì",
        "answer": "nông nghiệp lạc hậu:",
        "context": "Vào những năm 80 90 của thế kỉ XX, các nước này từng bước chuyển sang nên kinh tế thị trường Bước vào thời kì hoà bình xây dựng đất nước, nhân dân Lào đã đạt được một số thành tựu bước đẩu, nhưng về căn bản, Lào vẫn là một nước nông nghiệp lạc hậu: Từ cuối năm 1986, nước Lào thực hiện công cuộc đổi mới, nền kinh tế có sự khởi SdC , UUl S0llg CaC Uì [@C UuoC Cdl lmnlcl: UDI Ildll ZuUU lang J,/ 0, Sdll Xudl Ilong nghiệp tăng 4,59 , công nghiệp tăng 9,29 Sau khi tình hình chính trị ổn định, Campuchia bước vào thời kì phục hổi kinh tế và đạt được một số thành tựu đáng kể."
    },
    {
        "id": "p_31_2593",
        "question": "nền kinh tế của Lào là gì",
        "answer": "nông nghiệp lạc hậu:",
        "context": "Vào những năm 80 90 của thế kỉ XX, các nước này từng bước chuyển sang nên kinh tế thị trường Bước vào thời kì hoà bình xây dựng đất nước, nhân dân Lào đã đạt được một số thành tựu bước đẩu, nhưng về căn bản, Lào vẫn là một nước nông nghiệp lạc hậu: Từ cuối năm 1986, nước Lào thực hiện công cuộc đổi mới, nền kinh tế có sự khởi SdC , UUl S0llg CaC Uì [@C UuoC Cdl lmnlcl: UDI Ildll ZuUU lang J,/ 0, Sdll Xudl Ilong nghiệp tăng 4,59 , công nghiệp tăng 9,29 Sau khi tình hình chính trị ổn định, Campuchia bước vào thời kì phục hổi kinh tế và đạt được một số thành tựu đáng kể."
    },
    {
        "id": "p_31_2594",
        "question": "nền kinh tế của Campuchia bắt đầu khi nào",
        "answer": "Sau khi tình hình chính trị ổn định,",
        "context": "Vào những năm 80 90 của thế kỉ XX, các nước này từng bước chuyển sang nên kinh tế thị trường Bước vào thời kì hoà bình xây dựng đất nước, nhân dân Lào đã đạt được một số thành tựu bước đẩu, nhưng về căn bản, Lào vẫn là một nước nông nghiệp lạc hậu: Từ cuối năm 1986, nước Lào thực hiện công cuộc đổi mới, nền kinh tế có sự khởi SdC , UUl S0llg CaC Uì [@C UuoC Cdl lmnlcl: UDI Ildll ZuUU lang J,/ 0, Sdll Xudl Ilong nghiệp tăng 4,59 , công nghiệp tăng 9,29 Sau khi tình hình chính trị ổn định, Campuchia bước vào thời kì phục hổi kinh tế và đạt được một số thành tựu đáng kể."
    },
    {
        "id": "p_31_2595",
        "question": "nền kinh tế của Campuchia bắt đầu như thế nào",
        "answer": "Sau khi tình hình chính trị ổn định,",
        "context": "Vào những năm 80 90 của thế kỉ XX, các nước này từng bước chuyển sang nên kinh tế thị trường Bước vào thời kì hoà bình xây dựng đất nước, nhân dân Lào đã đạt được một số thành tựu bước đẩu, nhưng về căn bản, Lào vẫn là một nước nông nghiệp lạc hậu: Từ cuối năm 1986, nước Lào thực hiện công cuộc đổi mới, nền kinh tế có sự khởi SdC , UUl S0llg CaC Uì [@C UuoC Cdl lmnlcl: UDI Ildll ZuUU lang J,/ 0, Sdll Xudl Ilong nghiệp tăng 4,59 , công nghiệp tăng 9,29 Sau khi tình hình chính trị ổn định, Campuchia bước vào thời kì phục hổi kinh tế và đạt được một số thành tựu đáng kể."
    },
    {
        "id": "p_31_2596",
        "question": "nền kinh tế của Campuchia là gì",
        "answer": "công nghiệp tăng 9,29",
        "context": "Vào những năm 80 90 của thế kỉ XX, các nước này từng bước chuyển sang nên kinh tế thị trường Bước vào thời kì hoà bình xây dựng đất nước, nhân dân Lào đã đạt được một số thành tựu bước đẩu, nhưng về căn bản, Lào vẫn là một nước nông nghiệp lạc hậu: Từ cuối năm 1986, nước Lào thực hiện công cuộc đổi mới, nền kinh tế có sự khởi SdC , UUl S0llg CaC Uì [@C UuoC Cdl lmnlcl: UDI Ildll ZuUU lang J,/ 0, Sdll Xudl Ilong nghiệp tăng 4,59 , công nghiệp tăng 9,29 Sau khi tình hình chính trị ổn định, Campuchia bước vào thời kì phục hổi kinh tế và đạt được một số thành tựu đáng kể."
    },
    {
        "id": "p_31_2597",
        "question": "nền kinh tế của Campuchia bắt đầu vào năm nào",
        "answer": "năm 1986,",
        "context": "Vào những năm 80 90 của thế kỉ XX, các nước này từng bước chuyển sang nên kinh tế thị trường Bước vào thời kì hoà bình xây dựng đất nước, nhân dân Lào đã đạt được một số thành tựu bước đẩu, nhưng về căn bản, Lào vẫn là một nước nông nghiệp lạc hậu: Từ cuối năm 1986, nước Lào thực hiện công cuộc đổi mới, nền kinh tế có sự khởi SdC , UUl S0llg CaC Uì [@C UuoC Cdl lmnlcl: UDI Ildll ZuUU lang J,/ 0, Sdll Xudl Ilong nghiệp tăng 4,59 , công nghiệp tăng 9,29 Sau khi tình hình chính trị ổn định, Campuchia bước vào thời kì phục hổi kinh tế và đạt được một số thành tựu đáng kể."
    },
    {
        "id": "p_31_2598",
        "question": "nền kinh tế của Lào bắt đầu khi nào",
        "answer": "Từ cuối năm 1986,",
        "context": "Vào những năm 80 90 của thế kỉ XX, các nước này từng bước chuyển sang nên kinh tế thị trường Bước vào thời kì hoà bình xây dựng đất nước, nhân dân Lào đã đạt được một số thành tựu bước đẩu, nhưng về căn bản, Lào vẫn là một nước nông nghiệp lạc hậu: Từ cuối năm 1986, nước Lào thực hiện công cuộc đổi mới, nền kinh tế có sự khởi SdC , UUl S0llg CaC Uì [@C UuoC Cdl lmnlcl: UDI Ildll ZuUU lang J,/ 0, Sdll Xudl Ilong nghiệp tăng 4,59 , công nghiệp tăng 9,29 Sau khi tình hình chính trị ổn định, Campuchia bước vào thời kì phục hổi kinh tế và đạt được một số thành tựu đáng kể."
    },
    {
        "id": "p_31_2599",
        "question": "nền kinh tế của Lào bắt đầu như thế nào",
        "answer": "Từ cuối năm 1986, nước Lào thực hiện công cuộc đổi mới,",
        "context": "Vào những năm 80 90 của thế kỉ XX, các nước này từng bước chuyển sang nên kinh tế thị trường Bước vào thời kì hoà bình xây dựng đất nước, nhân dân Lào đã đạt được một số thành tựu bước đẩu, nhưng về căn bản, Lào vẫn là một nước nông nghiệp lạc hậu: Từ cuối năm 1986, nước Lào thực hiện công cuộc đổi mới, nền kinh tế có sự khởi SdC , UUl S0llg CaC Uì [@C UuoC Cdl lmnlcl: UDI Ildll ZuUU lang J,/ 0, Sdll Xudl Ilong nghiệp tăng 4,59 , công nghiệp tăng 9,29 Sau khi tình hình chính trị ổn định, Campuchia bước vào thời kì phục hổi kinh tế và đạt được một số thành tựu đáng kể."
    },
    {
        "id": "p_31_2600",
        "question": "nền kinh tế của Lào bắt đầu vào năm nào",
        "answer": "năm 1986,",
        "context": "Vào những năm 80 90 của thế kỉ XX, các nước này từng bước chuyển sang nên kinh tế thị trường Bước vào thời kì hoà bình xây dựng đất nước, nhân dân Lào đã đạt được một số thành tựu bước đẩu, nhưng về căn bản, Lào vẫn là một nước nông nghiệp lạc hậu: Từ cuối năm 1986, nước Lào thực hiện công cuộc đổi mới, nền kinh tế có sự khởi SdC , UUl S0llg CaC Uì [@C UuoC Cdl lmnlcl: UDI Ildll ZuUU lang J,/ 0, Sdll Xudl Ilong nghiệp tăng 4,59 , công nghiệp tăng 9,29 Sau khi tình hình chính trị ổn định, Campuchia bước vào thời kì phục hổi kinh tế và đạt được một số thành tựu đáng kể."
    },
    {
        "id": "p_31_2601",
        "question": "Campuchia có phải là một nước nông nghiệp không",
        "answer": "Campuchia vẫn là một nước nông nghiệp",
        "context": "Mặc dù sản xuất công nghiệp tăng 7% (1995), nhưng Campuchia vẫn là một nước nông nghiệp c) Các nước khác ở Đông Nam Á Nên kinh tế Brunây có nét khác biệt."
    },
    {
        "id": "p_31_2602",
        "question": "sự khác biệt giữa Campuchia và Ấn Độ là gì",
        "answer": "Các nước khác ở Đông Nam Á",
        "context": "Mặc dù sản xuất công nghiệp tăng 7% (1995), nhưng Campuchia vẫn là một nước nông nghiệp c) Các nước khác ở Đông Nam Á Nên kinh tế Brunây có nét khác biệt."
    },
    {
        "id": "p_31_2603",
        "question": "Campuchia có phải là nước nông nghiệp không",
        "answer": "Campuchia vẫn là một nước nông nghiệp",
        "context": "Mặc dù sản xuất công nghiệp tăng 7% (1995), nhưng Campuchia vẫn là một nước nông nghiệp c) Các nước khác ở Đông Nam Á Nên kinh tế Brunây có nét khác biệt."
    },
    {
        "id": "p_31_2604",
        "question": "campuchia có phải là một nước nông nghiệp không",
        "answer": "Campuchia vẫn là một nước nông nghiệp",
        "context": "Mặc dù sản xuất công nghiệp tăng 7% (1995), nhưng Campuchia vẫn là một nước nông nghiệp c) Các nước khác ở Đông Nam Á Nên kinh tế Brunây có nét khác biệt."
    },
    {
        "id": "p_31_2605",
        "question": "sự khác biệt giữa Campuchia và Úc là gì",
        "answer": "Các nước khác ở Đông Nam Á",
        "context": "Mặc dù sản xuất công nghiệp tăng 7% (1995), nhưng Campuchia vẫn là một nước nông nghiệp c) Các nước khác ở Đông Nam Á Nên kinh tế Brunây có nét khác biệt."
    },
    {
        "id": "p_31_2606",
        "question": "sự khác biệt giữa Campuchia và Brunây là gì",
        "answer": "Các nước khác ở Đông Nam Á",
        "context": "Mặc dù sản xuất công nghiệp tăng 7% (1995), nhưng Campuchia vẫn là một nước nông nghiệp c) Các nước khác ở Đông Nam Á Nên kinh tế Brunây có nét khác biệt."
    },
    {
        "id": "p_31_2607",
        "question": "các nước nông nghiệp khác nhau ở Campuchia là gì",
        "answer": "Các nước khác ở Đông Nam Á",
        "context": "Mặc dù sản xuất công nghiệp tăng 7% (1995), nhưng Campuchia vẫn là một nước nông nghiệp c) Các nước khác ở Đông Nam Á Nên kinh tế Brunây có nét khác biệt."
    },
    {
        "id": "p_31_2608",
        "question": "sự khác biệt giữa Campuchia và Ấn Độ là gì?",
        "answer": "Các nước khác ở Đông Nam Á",
        "context": "Mặc dù sản xuất công nghiệp tăng 7% (1995), nhưng Campuchia vẫn là một nước nông nghiệp c) Các nước khác ở Đông Nam Á Nên kinh tế Brunây có nét khác biệt."
    },
    {
        "id": "p_31_2609",
        "question": "Campuchia có phải là một nước nông nghiệp không?",
        "answer": "Campuchia vẫn là một nước nông nghiệp",
        "context": "Mặc dù sản xuất công nghiệp tăng 7% (1995), nhưng Campuchia vẫn là một nước nông nghiệp c) Các nước khác ở Đông Nam Á Nên kinh tế Brunây có nét khác biệt."
    },
    {
        "id": "p_31_2610",
        "question": "sự khác biệt giữa campuchia và Ấn Độ là gì",
        "answer": "Các nước khác ở Đông Nam Á",
        "context": "Mặc dù sản xuất công nghiệp tăng 7% (1995), nhưng Campuchia vẫn là một nước nông nghiệp c) Các nước khác ở Đông Nam Á Nên kinh tế Brunây có nét khác biệt."
    },
    {
        "id": "p_31_2611",
        "question": "lương thực của nguôn dẩu mỏ là bao nhiêu",
        "answer": "809.",
        "context": "Hẩu như toàn bộ thu nhập của nước này đều dưa vào nguôn dẩu mỏ và khí tự nhiên: Lương thực, thực phẩm phải nhập tới 809."
    },
    {
        "id": "p_31_2612",
        "question": "thu nhập trung bình của nguôn dẩu mỏ và khí tự nhiên là bao nhiêu",
        "answer": "809.",
        "context": "Hẩu như toàn bộ thu nhập của nước này đều dưa vào nguôn dẩu mỏ và khí tự nhiên: Lương thực, thực phẩm phải nhập tới 809."
    },
    {
        "id": "p_31_2613",
        "question": "thu nhập của nguôn dẩu mỏ là bao nhiêu",
        "answer": "809.",
        "context": "Hẩu như toàn bộ thu nhập của nước này đều dưa vào nguôn dẩu mỏ và khí tự nhiên: Lương thực, thực phẩm phải nhập tới 809."
    },
    {
        "id": "p_31_2614",
        "question": "lương thực của hẩu là bao nhiêu",
        "answer": "809.",
        "context": "Hẩu như toàn bộ thu nhập của nước này đều dưa vào nguôn dẩu mỏ và khí tự nhiên: Lương thực, thực phẩm phải nhập tới 809."
    },
    {
        "id": "p_31_2615",
        "question": "thu nhập trung bình của nguôn dẩu mỏ và khí tự nhiên",
        "answer": "Lương thực, thực phẩm phải nhập tới 809.",
        "context": "Hẩu như toàn bộ thu nhập của nước này đều dưa vào nguôn dẩu mỏ và khí tự nhiên: Lương thực, thực phẩm phải nhập tới 809."
    },
    {
        "id": "p_31_2616",
        "question": "lương thực của nguôn dẩu là bao nhiêu",
        "answer": "809.",
        "context": "Hẩu như toàn bộ thu nhập của nước này đều dưa vào nguôn dẩu mỏ và khí tự nhiên: Lương thực, thực phẩm phải nhập tới 809."
    },
    {
        "id": "p_31_2617",
        "question": "thu nhập trung bình của nguôn dẩu mỏ là bao nhiêu",
        "answer": "809.",
        "context": "Hẩu như toàn bộ thu nhập của nước này đều dưa vào nguôn dẩu mỏ và khí tự nhiên: Lương thực, thực phẩm phải nhập tới 809."
    },
    {
        "id": "p_31_2618",
        "question": "thu nhập trung bình của nguôn dẩu mỏ",
        "answer": "809.",
        "context": "Hẩu như toàn bộ thu nhập của nước này đều dưa vào nguôn dẩu mỏ và khí tự nhiên: Lương thực, thực phẩm phải nhập tới 809."
    },
    {
        "id": "p_31_2619",
        "question": "thu nhập trung bình của nguôn dẩu mỏ và khí tự nhiên là bao nhiêu?",
        "answer": "809.",
        "context": "Hẩu như toàn bộ thu nhập của nước này đều dưa vào nguôn dẩu mỏ và khí tự nhiên: Lương thực, thực phẩm phải nhập tới 809."
    },
    {
        "id": "p_31_2620",
        "question": "thu nhập trung bình của nguôn dẩu và khí tự nhiên là bao nhiêu",
        "answer": "809.",
        "context": "Hẩu như toàn bộ thu nhập của nước này đều dưa vào nguôn dẩu mỏ và khí tự nhiên: Lương thực, thực phẩm phải nhập tới 809."
    },
    {
        "id": "p_31_2621",
        "question": "chính sách đa dạng hoá nên kinh tế như thế nào",
        "answer": "tiết kiệm nguổn năng lượng dự trữ,",
        "context": "Từ giữa những năm 80 của thế kỉ XX, Chính phủ thi hành chính sách đa dạng hoá nên kinh tế để tiết kiệm nguổn năng lượng dự trữ, gia tăng các mặt hàng tiêu dùng và xuất khẩu."
    },
    {
        "id": "p_31_2622",
        "question": "chính sách đa dạng hoá nên kinh tế để tiết kiệm nguồn năng lượng dự trữ",
        "answer": "Chính phủ",
        "context": "Từ giữa những năm 80 của thế kỉ XX, Chính phủ thi hành chính sách đa dạng hoá nên kinh tế để tiết kiệm nguổn năng lượng dự trữ, gia tăng các mặt hàng tiêu dùng và xuất khẩu."
    },
    {
        "id": "p_31_2623",
        "question": "chính sách đa dạng hoá nên kinh tế khi nào",
        "answer": "Từ giữa những năm 80 của thế kỉ XX,",
        "context": "Từ giữa những năm 80 của thế kỉ XX, Chính phủ thi hành chính sách đa dạng hoá nên kinh tế để tiết kiệm nguổn năng lượng dự trữ, gia tăng các mặt hàng tiêu dùng và xuất khẩu."
    },
    {
        "id": "p_31_2624",
        "question": "chính sách đa dạng hoá nên kinh tế để tiết kiệm năng lượng dự trữ",
        "answer": "Chính phủ",
        "context": "Từ giữa những năm 80 của thế kỉ XX, Chính phủ thi hành chính sách đa dạng hoá nên kinh tế để tiết kiệm nguổn năng lượng dự trữ, gia tăng các mặt hàng tiêu dùng và xuất khẩu."
    },
    {
        "id": "p_31_2625",
        "question": "chính sách đa dạng hoá nên kinh tế để tiết kiệm nguồn năng lượng dự trữ là gì",
        "answer": "gia tăng các mặt hàng tiêu dùng và xuất khẩu.",
        "context": "Từ giữa những năm 80 của thế kỉ XX, Chính phủ thi hành chính sách đa dạng hoá nên kinh tế để tiết kiệm nguổn năng lượng dự trữ, gia tăng các mặt hàng tiêu dùng và xuất khẩu."
    },
    {
        "id": "p_31_2626",
        "question": "chính sách đa dạng hoá nên kinh tế",
        "answer": "tiết kiệm nguổn năng lượng dự trữ,",
        "context": "Từ giữa những năm 80 của thế kỉ XX, Chính phủ thi hành chính sách đa dạng hoá nên kinh tế để tiết kiệm nguổn năng lượng dự trữ, gia tăng các mặt hàng tiêu dùng và xuất khẩu."
    },
    {
        "id": "p_31_2627",
        "question": "chính sách đa dạng hoá nên kinh tế để tiết kiệm nguồn năng lượng dự trữ và xuất khẩu",
        "answer": "Chính phủ",
        "context": "Từ giữa những năm 80 của thế kỉ XX, Chính phủ thi hành chính sách đa dạng hoá nên kinh tế để tiết kiệm nguổn năng lượng dự trữ, gia tăng các mặt hàng tiêu dùng và xuất khẩu."
    },
    {
        "id": "p_31_2628",
        "question": "chính sách đa dạng hoá nên kinh tế để tiết kiệm nguổn năng lượng dự trữ",
        "answer": "Chính phủ",
        "context": "Từ giữa những năm 80 của thế kỉ XX, Chính phủ thi hành chính sách đa dạng hoá nên kinh tế để tiết kiệm nguổn năng lượng dự trữ, gia tăng các mặt hàng tiêu dùng và xuất khẩu."
    },
    {
        "id": "p_31_2629",
        "question": "chính sách đa dạng hoá nên kinh tế để tiết kiệm năng lượng dự trữ là gì",
        "answer": "gia tăng các mặt hàng tiêu dùng và xuất khẩu.",
        "context": "Từ giữa những năm 80 của thế kỉ XX, Chính phủ thi hành chính sách đa dạng hoá nên kinh tế để tiết kiệm nguổn năng lượng dự trữ, gia tăng các mặt hàng tiêu dùng và xuất khẩu."
    },
    {
        "id": "p_31_2630",
        "question": "chính sách đa dạng hoá nên kinh tế để tiết kiệm năng lượng dự trữ và xuất khẩu",
        "answer": "Từ giữa những năm 80 của thế kỉ XX, Chính phủ",
        "context": "Từ giữa những năm 80 của thế kỉ XX, Chính phủ thi hành chính sách đa dạng hoá nên kinh tế để tiết kiệm nguổn năng lượng dự trữ, gia tăng các mặt hàng tiêu dùng và xuất khẩu."
    },
    {
        "id": "p_31_2631",
        "question": "mianma có kinh tế chậm chạp không",
        "answer": "tăng trưởng kinh tế chậm chạp.",
        "context": "Sau gẩn 30 năm thực hiện chính sách tự lực hướng nội của chính quyền quân sự, Mianma có tốc độ tăng trưởng kinh tế chậm chạp."
    },
    {
        "id": "p_31_2632",
        "question": "mianma có kinh tế như thế nào",
        "answer": "tốc độ tăng trưởng kinh tế chậm chạp.",
        "context": "Sau gẩn 30 năm thực hiện chính sách tự lực hướng nội của chính quyền quân sự, Mianma có tốc độ tăng trưởng kinh tế chậm chạp."
    },
    {
        "id": "p_31_2633",
        "question": "chính sách tự lực hướng nội của quân đội mianma là gì",
        "answer": "Mianma có tốc độ tăng trưởng kinh tế chậm chạp.",
        "context": "Sau gẩn 30 năm thực hiện chính sách tự lực hướng nội của chính quyền quân sự, Mianma có tốc độ tăng trưởng kinh tế chậm chạp."
    },
    {
        "id": "p_31_2634",
        "question": "kinh tế của mianma là gì",
        "answer": "tăng trưởng kinh tế chậm chạp.",
        "context": "Sau gẩn 30 năm thực hiện chính sách tự lực hướng nội của chính quyền quân sự, Mianma có tốc độ tăng trưởng kinh tế chậm chạp."
    },
    {
        "id": "p_31_2635",
        "question": "chính sách tự lực hướng nội của mianma là gì",
        "answer": "Mianma có tốc độ tăng trưởng kinh tế chậm chạp.",
        "context": "Sau gẩn 30 năm thực hiện chính sách tự lực hướng nội của chính quyền quân sự, Mianma có tốc độ tăng trưởng kinh tế chậm chạp."
    },
    {
        "id": "p_31_2636",
        "question": "chính sách tự lực hướng nội ở mianma là gì",
        "answer": "Mianma có tốc độ tăng trưởng kinh tế chậm chạp.",
        "context": "Sau gẩn 30 năm thực hiện chính sách tự lực hướng nội của chính quyền quân sự, Mianma có tốc độ tăng trưởng kinh tế chậm chạp."
    },
    {
        "id": "p_31_2637",
        "question": "chính sách tự lực hướng nội của quân đội là gì",
        "answer": "Mianma có tốc độ tăng trưởng kinh tế chậm chạp.",
        "context": "Sau gẩn 30 năm thực hiện chính sách tự lực hướng nội của chính quyền quân sự, Mianma có tốc độ tăng trưởng kinh tế chậm chạp."
    },
    {
        "id": "p_31_2638",
        "question": "chính sách tự lực hướng nội của quân đội ở mianma là gì",
        "answer": "Mianma có tốc độ tăng trưởng kinh tế chậm chạp.",
        "context": "Sau gẩn 30 năm thực hiện chính sách tự lực hướng nội của chính quyền quân sự, Mianma có tốc độ tăng trưởng kinh tế chậm chạp."
    },
    {
        "id": "p_31_2639",
        "question": "mianma có kinh tế chậm chạp không?",
        "answer": "tăng trưởng kinh tế chậm chạp.",
        "context": "Sau gẩn 30 năm thực hiện chính sách tự lực hướng nội của chính quyền quân sự, Mianma có tốc độ tăng trưởng kinh tế chậm chạp."
    },
    {
        "id": "p_31_2640",
        "question": "chính sách tự lực hướng nội của quân đội mianma là gì?",
        "answer": "Mianma có tốc độ tăng trưởng kinh tế chậm chạp.",
        "context": "Sau gẩn 30 năm thực hiện chính sách tự lực hướng nội của chính quyền quân sự, Mianma có tốc độ tăng trưởng kinh tế chậm chạp."
    },
    {
        "id": "p_31_2641",
        "question": "khi nào chính phủ tiến hành cải cách kinh tế",
        "answer": "cuối năm 1988,",
        "context": "Từ cuối năm 1988, Chính phủ tiến hành cải cách kinh tế và mở cửa\" , do đó nên kinh tế có sư khởi sắc."
    },
    {
        "id": "p_31_2642",
        "question": "khi nào chính phủ tiến hành cải cách kinh tế và mở cửa",
        "answer": "cuối năm 1988,",
        "context": "Từ cuối năm 1988, Chính phủ tiến hành cải cách kinh tế và mở cửa\" , do đó nên kinh tế có sư khởi sắc."
    },
    {
        "id": "p_31_2643",
        "question": "khi nào chính phủ tiến hành cải cách kinh tế và mở cửa?",
        "answer": "cuối năm 1988,",
        "context": "Từ cuối năm 1988, Chính phủ tiến hành cải cách kinh tế và mở cửa\" , do đó nên kinh tế có sư khởi sắc."
    },
    {
        "id": "p_31_2644",
        "question": "cải cách kinh tế và mở cửa là gì",
        "answer": "Chính phủ",
        "context": "Từ cuối năm 1988, Chính phủ tiến hành cải cách kinh tế và mở cửa\" , do đó nên kinh tế có sư khởi sắc."
    },
    {
        "id": "p_31_2645",
        "question": "khi nào kinh tế mở cửa",
        "answer": "Từ cuối năm 1988,",
        "context": "Từ cuối năm 1988, Chính phủ tiến hành cải cách kinh tế và mở cửa\" , do đó nên kinh tế có sư khởi sắc."
    },
    {
        "id": "p_31_2646",
        "question": "khi nào chính phủ tiến hành cải cách kinh tế?",
        "answer": "cuối năm 1988,",
        "context": "Từ cuối năm 1988, Chính phủ tiến hành cải cách kinh tế và mở cửa\" , do đó nên kinh tế có sư khởi sắc."
    },
    {
        "id": "p_31_2647",
        "question": "khi nào kinh tế của chúng tôi mở cửa",
        "answer": "Từ cuối năm 1988,",
        "context": "Từ cuối năm 1988, Chính phủ tiến hành cải cách kinh tế và mở cửa\" , do đó nên kinh tế có sư khởi sắc."
    },
    {
        "id": "p_31_2648",
        "question": "cải cách kinh tế và mở cửa được thực hiện khi nào",
        "answer": "cuối năm 1988,",
        "context": "Từ cuối năm 1988, Chính phủ tiến hành cải cách kinh tế và mở cửa\" , do đó nên kinh tế có sư khởi sắc."
    },
    {
        "id": "p_31_2649",
        "question": "cải cách kinh tế đã xảy ra vào năm nào",
        "answer": "năm 1988,",
        "context": "Từ cuối năm 1988, Chính phủ tiến hành cải cách kinh tế và mở cửa\" , do đó nên kinh tế có sư khởi sắc."
    },
    {
        "id": "p_31_2650",
        "question": "cải cách kinh tế là gì",
        "answer": "Chính phủ tiến hành cải cách kinh tế và mở cửa\"",
        "context": "Từ cuối năm 1988, Chính phủ tiến hành cải cách kinh tế và mở cửa\" , do đó nên kinh tế có sư khởi sắc."
    },
    {
        "id": "p_31_2651",
        "question": "thu nhập đầu người ở mianma là bao nhiêu",
        "answer": "(hơn 100 USD năm 2003) 3.",
        "context": "Tốc độ tang trưong GDP nam 1999 la /%o, nam 2UUU la 6,2%  Iuy nhlen, binh quan thu nhập đầu người ở Mianma còn thấp (hơn 100 USD năm 2003) 3."
    },
    {
        "id": "p_31_2652",
        "question": "tốc độ tang trưong ở mianma là bao nhiêu",
        "answer": "1999 la /%o,",
        "context": "Tốc độ tang trưong GDP nam 1999 la /%o, nam 2UUU la 6,2%  Iuy nhlen, binh quan thu nhập đầu người ở Mianma còn thấp (hơn 100 USD năm 2003) 3."
    },
    {
        "id": "p_31_2653",
        "question": "tốc độ tang trưong của mianma là bao nhiêu",
        "answer": "1999 la /%o,",
        "context": "Tốc độ tang trưong GDP nam 1999 la /%o, nam 2UUU la 6,2%  Iuy nhlen, binh quan thu nhập đầu người ở Mianma còn thấp (hơn 100 USD năm 2003) 3."
    },
    {
        "id": "p_31_2654",
        "question": "tốc độ tang trưong gdp ở mianma là bao nhiêu",
        "answer": "1999 la /%o,",
        "context": "Tốc độ tang trưong GDP nam 1999 la /%o, nam 2UUU la 6,2%  Iuy nhlen, binh quan thu nhập đầu người ở Mianma còn thấp (hơn 100 USD năm 2003) 3."
    },
    {
        "id": "p_31_2655",
        "question": "thu nhập của mianma là bao nhiêu",
        "answer": "(hơn 100 USD",
        "context": "Tốc độ tang trưong GDP nam 1999 la /%o, nam 2UUU la 6,2%  Iuy nhlen, binh quan thu nhập đầu người ở Mianma còn thấp (hơn 100 USD năm 2003) 3."
    },
    {
        "id": "p_31_2656",
        "question": "gdp của mianma là bao nhiêu",
        "answer": "(hơn 100 USD năm 2003) 3.",
        "context": "Tốc độ tang trưong GDP nam 1999 la /%o, nam 2UUU la 6,2%  Iuy nhlen, binh quan thu nhập đầu người ở Mianma còn thấp (hơn 100 USD năm 2003) 3."
    },
    {
        "id": "p_31_2657",
        "question": "tốc độ tang trưong mianma là bao nhiêu",
        "answer": "1999 la /%o,",
        "context": "Tốc độ tang trưong GDP nam 1999 la /%o, nam 2UUU la 6,2%  Iuy nhlen, binh quan thu nhập đầu người ở Mianma còn thấp (hơn 100 USD năm 2003) 3."
    },
    {
        "id": "p_31_2658",
        "question": "gdp ở mianma là bao nhiêu",
        "answer": "(hơn 100 USD năm 2003) 3.",
        "context": "Tốc độ tang trưong GDP nam 1999 la /%o, nam 2UUU la 6,2%  Iuy nhlen, binh quan thu nhập đầu người ở Mianma còn thấp (hơn 100 USD năm 2003) 3."
    },
    {
        "id": "p_31_2659",
        "question": "tốc độ tang trưong gdp là bao nhiêu",
        "answer": "1999 la /%o,",
        "context": "Tốc độ tang trưong GDP nam 1999 la /%o, nam 2UUU la 6,2%  Iuy nhlen, binh quan thu nhập đầu người ở Mianma còn thấp (hơn 100 USD năm 2003) 3."
    },
    {
        "id": "p_31_2660",
        "question": "thu nhập trung bình của mianma là bao nhiêu",
        "answer": "(hơn 100 USD năm 2003) 3.",
        "context": "Tốc độ tang trưong GDP nam 1999 la /%o, nam 2UUU la 6,2%  Iuy nhlen, binh quan thu nhập đầu người ở Mianma còn thấp (hơn 100 USD năm 2003) 3."
    },
    {
        "id": "p_31_2661",
        "question": "sự phát triển của tổ chức aSEAN là gì",
        "answer": "trong bối cảnh khu vực và thế giới có nhiều biến chuyển to lớn",
        "context": "Sự ra đời và phát triển của tổ chức ASEAN ASEAN ra đời trong bối cảnh khu vực và thế giới có nhiều biến chuyển to lớn vào nửa sau những năm 60 của thế kỉ XX. (1) Phần này chỉ đề cập nội dung về lịch sử Lào và Campuchia, còn nội dung vể Việt Nam sẽ được đề cập kĩ trong các bài lich sư Việt Nam ở phẩn sau."
    },
    {
        "id": "p_31_2662",
        "question": "tổ chức aSEAN được thành lập vào năm nào",
        "answer": "năm 60 của thế kỉ XX.",
        "context": "Sự ra đời và phát triển của tổ chức ASEAN ASEAN ra đời trong bối cảnh khu vực và thế giới có nhiều biến chuyển to lớn vào nửa sau những năm 60 của thế kỉ XX. (1) Phần này chỉ đề cập nội dung về lịch sử Lào và Campuchia, còn nội dung vể Việt Nam sẽ được đề cập kĩ trong các bài lich sư Việt Nam ở phẩn sau."
    },
    {
        "id": "p_31_2663",
        "question": "sự phát triển của tổ chức anean là gì",
        "answer": "trong bối cảnh khu vực và thế giới có nhiều biến chuyển to lớn",
        "context": "Sự ra đời và phát triển của tổ chức ASEAN ASEAN ra đời trong bối cảnh khu vực và thế giới có nhiều biến chuyển to lớn vào nửa sau những năm 60 của thế kỉ XX. (1) Phần này chỉ đề cập nội dung về lịch sử Lào và Campuchia, còn nội dung vể Việt Nam sẽ được đề cập kĩ trong các bài lich sư Việt Nam ở phẩn sau."
    },
    {
        "id": "p_31_2664",
        "question": "sự phát triển của tổ chức aSEAN là gì?",
        "answer": "trong bối cảnh khu vực và thế giới có nhiều biến chuyển to lớn",
        "context": "Sự ra đời và phát triển của tổ chức ASEAN ASEAN ra đời trong bối cảnh khu vực và thế giới có nhiều biến chuyển to lớn vào nửa sau những năm 60 của thế kỉ XX. (1) Phần này chỉ đề cập nội dung về lịch sử Lào và Campuchia, còn nội dung vể Việt Nam sẽ được đề cập kĩ trong các bài lich sư Việt Nam ở phẩn sau."
    },
    {
        "id": "p_31_2665",
        "question": "tổ chức aSEAN ra đời và phát triển như thế nào",
        "answer": "trong bối cảnh khu vực và thế giới có nhiều biến chuyển to lớn",
        "context": "Sự ra đời và phát triển của tổ chức ASEAN ASEAN ra đời trong bối cảnh khu vực và thế giới có nhiều biến chuyển to lớn vào nửa sau những năm 60 của thế kỉ XX. (1) Phần này chỉ đề cập nội dung về lịch sử Lào và Campuchia, còn nội dung vể Việt Nam sẽ được đề cập kĩ trong các bài lich sư Việt Nam ở phẩn sau."
    },
    {
        "id": "p_31_2666",
        "question": "tổ chức aSEAN được thành lập khi nào",
        "answer": "nửa sau những năm 60 của thế kỉ XX.",
        "context": "Sự ra đời và phát triển của tổ chức ASEAN ASEAN ra đời trong bối cảnh khu vực và thế giới có nhiều biến chuyển to lớn vào nửa sau những năm 60 của thế kỉ XX. (1) Phần này chỉ đề cập nội dung về lịch sử Lào và Campuchia, còn nội dung vể Việt Nam sẽ được đề cập kĩ trong các bài lich sư Việt Nam ở phẩn sau."
    },
    {
        "id": "p_31_2667",
        "question": "sự phát triển của tổ chức asen là gì",
        "answer": "trong bối cảnh khu vực và thế giới có nhiều biến chuyển to lớn",
        "context": "Sự ra đời và phát triển của tổ chức ASEAN ASEAN ra đời trong bối cảnh khu vực và thế giới có nhiều biến chuyển to lớn vào nửa sau những năm 60 của thế kỉ XX. (1) Phần này chỉ đề cập nội dung về lịch sử Lào và Campuchia, còn nội dung vể Việt Nam sẽ được đề cập kĩ trong các bài lich sư Việt Nam ở phẩn sau."
    },
    {
        "id": "p_31_2668",
        "question": "sự phát triển của tổ chức aSEAN là khi nào",
        "answer": "những năm 60 của thế kỉ XX.",
        "context": "Sự ra đời và phát triển của tổ chức ASEAN ASEAN ra đời trong bối cảnh khu vực và thế giới có nhiều biến chuyển to lớn vào nửa sau những năm 60 của thế kỉ XX. (1) Phần này chỉ đề cập nội dung về lịch sử Lào và Campuchia, còn nội dung vể Việt Nam sẽ được đề cập kĩ trong các bài lich sư Việt Nam ở phẩn sau."
    },
    {
        "id": "p_31_2669",
        "question": "tổ chức aSEAN ra đời và phát triển khi nào",
        "answer": "những năm 60 của thế kỉ XX.",
        "context": "Sự ra đời và phát triển của tổ chức ASEAN ASEAN ra đời trong bối cảnh khu vực và thế giới có nhiều biến chuyển to lớn vào nửa sau những năm 60 của thế kỉ XX. (1) Phần này chỉ đề cập nội dung về lịch sử Lào và Campuchia, còn nội dung vể Việt Nam sẽ được đề cập kĩ trong các bài lich sư Việt Nam ở phẩn sau."
    },
    {
        "id": "p_31_2670",
        "question": "tổ chức aSEAN ra đời khi nào",
        "answer": "nửa sau những năm 60 của thế kỉ XX.",
        "context": "Sự ra đời và phát triển của tổ chức ASEAN ASEAN ra đời trong bối cảnh khu vực và thế giới có nhiều biến chuyển to lớn vào nửa sau những năm 60 của thế kỉ XX. (1) Phần này chỉ đề cập nội dung về lịch sử Lào và Campuchia, còn nội dung vể Việt Nam sẽ được đề cập kĩ trong các bài lich sư Việt Nam ở phẩn sau."
    }
]